Workbook

Sheet Portada
B2: CHECKLIST INTEGRADO DE CUMPLIMIENTO — LEY N° 21.719
B3: Integra RAT, ARCOP, transferencias, ISO/IEC 27001:2022, NIST CSF 2.0, CIS, COBIT, PCI DSS y normativa chilena
B5: Organización | C5: [Completar]
B6: Responsable de cumplimiento | C6: [Completar]
B7: Fecha de evaluación | C7: [Completar]
B8: Próxima revisión | C8: [Completar]
B9: Evaluador | C9: [Completar]
B11: CÓMO FUNCIONA
B12: 1. Controles marcos: asignar a cada control (ISO, NIST, CIS, COBIT, PCI y normativa) un puntaje de 1 a 5, o N/A si no aplica.
B13: 2. RAT, ARCOP y Transferencias: mantener los registros. Los indicadores de la hoja Resumen se calculan solos desde ahí.
B14: 3. Requisitos Ley: el puntaje de cada requisito es el promedio de sus controles mapeados (y de sus indicadores, cuando corresponda). No se asigna puntaje manual.
B15: 4. Resumen: puntaje por dimensión, total ponderado, vista por marco y por función NIST / tema ISO.
B16: 5. Un requisito sin controles puntuados queda en blanco y no pesa en el total.

Sheet Disclaimer
B2: DISCLAIMER, CONFIDENCIALIDAD Y ACEPTACIÓN DE LA INFORMACIÓN
B3: Levantamiento preliminar (discovery) — Ley N° 21.719 sobre protección de datos personales
B5: 1. Naturaleza del documento | C5: Este archivo es un levantamiento preliminar (discovery) para identificar brechas de cumplimiento y dimensionar la etapa de remediación. No constituye auditoría, certificación, dictamen ni asesoría legal. Para conclusiones jurídicas definitivas, consulte a un abogado especialista.
B6: 2. Base de la información | C6: Los puntajes se calculan a partir de la información que entrega la organización y de las entrevistas realizadas. Salvo que se indique lo contrario, la información no ha sido verificada de forma independiente. Los puntajes son indicativos y pueden cambiar con evidencia adicional.
B7: 3. Marco normativo | C7: Las referencias a la Ley 21.719 corresponden a la versión disponible al momento de la evaluación. La ley entra en vigencia el 1 de diciembre de 2026; existe un proyecto para postergarla. Los artículos y plazos citados deben validarse contra el texto oficial publicado en la Biblioteca del Congreso Nacional (BCN). Las sanciones no forman parte de este análisis.
B8: 4. Datos personales en este archivo | C8: Este archivo debe contener la menor cantidad posible de datos personales. En los registros de actividades, solicitudes ARCOP y transferencias use identificadores internos o iniciales, nunca nombres completos, RUT, correos ni datos de salud de personas. Si la información sensible es necesaria para el diagnóstico, regístrela de forma agregada.
B9: 5. Clasificación y acceso | C9: Este archivo y su contenido se consideran CONFIDENCIALES. Compártalo solo con personas autorizadas por la dirección de la organización. No lo reenvíe por canales no corporativos ni lo publique.
B10: 6. Entrevistas y aviso a entrevistados | C10: Las entrevistas tienen por finalidad diagnosticar el estado de cumplimiento de la organización. Antes de iniciarlas, informe al entrevistado que sus respuestas se registran en este archivo, quién las usará y por cuánto tiempo se conservarán. Si se graban o se toman fotos o documentos personales, obtenga su consentimiento previo.
B11: 7. Responsabilidad | C11: La organización es responsable de la veracidad y completitud de la información entregada. El evaluador no responde por decisiones tomadas con base en este archivo sin validación adicional.
B12: 8. Uso del resultado | C12: El resultado sirve para priorizar la remediación. Antes de implementar cambios, valide cada brecha con su área responsable y con asesoría legal cuando corresponda.
B14: ACEPTACIÓN
C15: Complete los campos amarillos. Al responder 'Sí', usted declara haber leído y aceptado las condiciones anteriores.
B16: Organización evaluada
B17: Nombre de quien acepta
B18: Cargo
B19: Fecha de aceptación (dd/mm/aaaa)
B20: ¿Acepta las condiciones? (Sí/No)
B21: Observaciones
B22: Firma (nombre escrito)

Sheet Cómo llenar
B1: CÓMO LLENAR ESTE CHECKLIST
B2: Regla básica: las celdas AMARILLAS son las únicas que puede editar. El resto está bloqueado para evitar cambios por error.
B3: Sin contraseña. Si necesita cambiar una fórmula: Revisar > Desproteger hoja. Vuelva a proteger al terminar.
A5: Paso | B5: Hoja | C5: Qué hacer | D5: Valores aceptados | E5: Ejemplo
A6: 1 | B6: Portada | C6: Escriba el nombre de la organización, el responsable, la fecha de evaluación, la próxima revisión y el evaluador. | D6: Texto libre. Fechas en formato dd/mm/aaaa. | E6: Fecha de evaluación: 19/10/2026
A7: 2 | B7: RAT | C7: Una fila por cada actividad de tratamiento de datos personales. Complete las columnas B a P. La columna Q (completitud) se calcula sola: 100% = las 15 columnas llenas. | D7: Base legal: elija de la lista. Datos sensibles: Sí o No. Última revisión: dd/mm/aaaa. El resto, texto. | E7: RAT-007 · Gestión de postventa · Lit. b — Ejecución de contrato
A8: 3 | B8: ARCOP | C8: Una fila por cada solicitud de derechos del titular. Tipo y Estado se eligen de la lista. La columna Estado de plazo se calcula sola (A tiempo, Fuera de plazo, En plazo o Vencida). | D8: Tipo: lista. Estado: Pendiente, En proceso, Respondido o Rechazado. Fechas dd/mm/aaaa. Fecha límite: 30 días corridos desde la recepción (verifique el plazo en el texto oficial). | E8: ARC-005 · Acceso · recibida 02/10/2026 · límite 01/11/2026
A9: 4 | B9: Transferencias | C9: Una fila por cada destinatario fuera de Chile. Use el mismo ID del RAT. La columna Garantía definida se calcula sola: Sí si escribió la garantía. | D9: ID RAT: el mismo de la hoja RAT. Garantías: texto (por ejemplo, SCC + DPA). | E9: RAT-003 · Mailchimp · EE.UU. · SCC + DPA
A10: 5 | B10: Controles marcos | C10: Para cada control, lea en la columna C qué debe levantar. El puntaje se calcula solo a partir de la hoja Registro entrevistas: registre allí cada entrevista y su evidencia verificada. Use N/A solo si el control no aplica, y justifique en la columna Evidencia (escriba la razón en esa celda). | D10: 1, 2, 3, 4, 5 o N/A. Guía de niveles en la hoja Escala. | E10: ISO 8.7 · 4 (EDR en todos los endpoints, sin revisión trimestral)
A11: 6 | B11: Requisitos Ley | C11: No se puntúa aquí: el puntaje sale del promedio de los controles mapeados. Complete Evidencia, Brecha / plan de acción, Responsable y Fecha límite. Para incluir u omitir requisitos extra, cambie 'Incluir en puntaje' (columna K): Sí o No. | D11: Texto libre. Fecha límite en dd/mm/aaaa. | E11: Brecha: falta matriz de accesos. Responsable: CISO. Fecha: 30/11/2026
A12: 7 | B12: Resumen | C12: Ajuste el peso de cada dimensión si su organización lo requiere. Los pesos deben sumar 100%. | D12: Porcentaje entre 0% y 100%. La celda de control debe decir 'Pesos correctos'. | E12: D8 Seguridad: 11%
A13: 8 | B13: Entrevistas | C13: Prepare y registre cada entrevista por dimensión: quién consultar, qué preguntar y qué evidencia pedir. Lo que escriba aquí no cambia el puntaje; úselo para puntuar los controles. | D13: Texto libre. Puntaje sugerido: 1 a 5 o N/A. | E13: Gerencia de RRHH: contratos sin cláusulas de privacidad; expedientes en papel sin control de acceso.
A14: 9 | B14: Dashboard | C14: No se edita. Revise el resultado después de completar los pasos anteriores. | D14: — | E14: Si aparece 'Cobertura insuficiente', faltan requisitos por evaluar.
B16: ORDEN RECOMENDADO
B17: 1 → 2 → 3 → 4 → 5 → 6 → 7 → revisar el Dashboard. Los pasos 2, 3 y 4 alimentan indicadores que afectan los requisitos de la ley.
B19: ERRORES COMUNES
B20: • Una fecha escrita como texto no se reconoce en el cálculo de plazos. Use dd/mm/aaaa.
B21: • Si una celda muestra un aviso amarillo al escribir, revise el valor. Puede guardarlo, pero el cálculo puede no reflejarlo.
B22: • No borre fórmulas de las columnas Q (RAT), I (ARCOP) ni J (Transferencias). Están bloqueadas.
B23: • Un requisito sin controles puntuados aparece en blanco y no pesa en el total. Por eso el Dashboard muestra la cobertura.

Sheet Entrevistas
A1: GUÍA DE ENTREVISTAS POR DIMENSIÓN
A2: Guía de preguntas por dimensión para preparar cada entrevista. Para registrar lo que responde la persona, use la hoja Registro entrevistas: el puntaje se calcula desde allí.
A4: Código | B4: Dimensión | C4: Entrevistado sugerido | D4: Preguntas clave | E4: Evidencia a solicitar | F4: Fecha entrevista | G4: Entrevistado real | H4: Hallazgos | I4: Puntaje sugerido (1-5)
A5: D1 | B5: Gobierno y responsabilidad proactiva | C5: Gerencia General / Directorio | D5: 1. ¿Quién aprobó la política de privacidad y cuándo se revisó por última vez? 2. ¿Existe un responsable de privacidad con recursos asignados? 3. ¿Cómo demuestra el cumplimiento si la autoridad lo solicita? | E5: Política aprobada, acta de directorio, organigrama con roles
A6: D2 | B6: Inventario y Registro de Actividades de Tratamiento (RAT) | C6: Gerencia de TI y responsable de datos | D6: 1. ¿Existe un inventario de sistemas que tratan datos personales? 2. ¿Quién mantiene el RAT y cuándo se actualizó? | E6: RAT vigente, inventario de sistemas
A7: D3 | B7: Licitud del tratamiento y consentimiento | C7: Gerencia Comercial y Marketing | D7: 1. ¿Con qué base legal se trata cada base de datos? 2. ¿Cómo se registra el consentimiento y cómo se revoca? | E7: Formularios de consentimiento, registro de consentimientos
A8: D4 | B8: Derechos de los titulares (ARCOP) | C8: Servicio al cliente | D8: 1. ¿Cómo llegan las solicitudes ARCOP y quién las responde? 2. ¿Cuánto demoran en promedio y cómo verifican la identidad del solicitante? | E8: Registro de solicitudes ARCOP, procedimiento
A9: D5 | B9: Principios y ciclo de vida del dato | C9: Dueños de procesos (Comercial, RRHH, Finanzas) | D9: 1. ¿Qué datos piden y para qué los usan? 2. ¿Cuánto tiempo guardan cada categoría y cómo la eliminan? | E9: Política de retención, evidencia de eliminación
A10: D6 | B10: Datos sensibles, biométricos y de menores | C10: RRHH y Seguridad | D10: 1. ¿Recolectan datos de salud, licencias médicas o biométricos? 2. ¿Quién accede a ellos? | E10: Inventario de datos sensibles, controles de acceso
A11: D7 | B11: Evaluación de impacto y privacidad desde el diseño | C11: Gerencia de TI y de proyectos | D11: 1. ¿Se evalúa la privacidad antes de lanzar un sistema o campaña? 2. ¿Hay EIPD documentada para tratamientos de alto riesgo (videovigilancia, biometría, perfilamiento)? | E11: EIPD, checklist de privacidad en proyectos
A12: D8 | B12: Seguridad de la información (RBAC, malware, MFA) | C12: CISO / Jefe de TI | D12: 1. ¿Cómo se gestionan accesos y roles (RBAC)? 2. ¿En qué sistemas hay MFA y qué antivirus o EDR usan? 3. ¿Cuándo fue la última prueba de intrusión? | E12: Matriz de accesos, reportes EDR, informe de pentest
A13: D9 | B13: Gestión de incidentes, continuidad y DRP | C13: CISO y Gerencia de Operaciones | D13: 1. ¿Qué pasa si hay una brecha de datos un viernes en la noche? 2. ¿Cuándo fue la última prueba de restauración y del plan de recuperación? | E13: IRP, registro de simulacros, pruebas de restauración
A14: D10 | B14: Encargados, proveedores y transferencias internacionales | C14: Compras / Administración | D14: 1. ¿Qué proveedores tratan datos personales? 2. ¿Sus contratos tienen cláusulas de privacidad y eliminación al término? ¿Tienen sub-encargados? | E14: Contratos, inventario de proveedores
A15: D11 | B15: Capacitación, cultura y phishing | C15: RRHH y Capacitación | D15: 1. ¿Cuántas personas completaron capacitación en privacidad el último año? 2. ¿Hacen simulacros de phishing y con qué resultados? | E15: Registro de capacitación, resultados de simulacros
A16: D12 | B16: Auditoría, monitoreo y mejora continua | C16: Auditoría interna / Gerencia General | D16: 1. ¿Qué indicadores de privacidad se reportan y con qué frecuencia? 2. ¿Existe un plan de auditoría anual? | E16: Plan de auditoría, informes, indicadores
... A22: D18 | B22: Clientes, leads, prospectos y marketing | C22: Gerencia de Marketing y Ecommerce | D22: 1. ¿De dónde vienen las bases de datos de leads y prospectos? ¿Compran listas? 2. ¿Usan cookies o seguimiento de terceros? ¿Hacen perfilamiento? 3. ¿Cómo atienden el opt-out y cuánto conservan leads inactivos? | E22: Formularios de consentimiento, política de cookies, contratos con proveedores de listas

Sheet Registro entrevistas
A1: REGISTRO DE ENTREVISTAS Y CONSOLIDACIÓN DEL PUNTAJE POR CONTROL
A3: CÓMO SE USA
A4: Paso 1 | B4: Registre una fila por entrevista y por control evaluado. No registre una fila por dimensión: un control puede tener varias entrevistas (una por área).
A5: Paso 2 | B5: Escriba en 'Lo que afirma el entrevistado' la respuesta resumida, y en 'Evidencia solicitada' el documento o muestra que pidió.
A6: Paso 3 | B6: Marque 'Evidencia verificada' en Sí solo si usted revisó el documento o la muestra. Si solo hay una afirmación verbal, marque No.
A7: Paso 4 | B7: Asigne el 'Puntaje propuesto' (1 a 5 o N/A) con la escala de la hoja Escala.
A8: Paso 5 | B8: El puntaje de cada control aparece solo en la hoja Controles marcos (columna E). No se escribe a mano.
A9: POR QUÉ SE USA EL MÍNIMO VERIFICADO
A10: Regla | B10: El puntaje de un control es el MÍNIMO de los puntajes propuestos que tienen evidencia verificada.
A11: Razón 1 | B11: Un control vale lo que vale su punto más débil. Si un área dice 4 y otra muestra que el control no opera (1), el promedio daría 2,5 y ocultaría la brecha. El mínimo la muestra.
A12: Razón 2 | B12: El promedio premia a quien responde mejor. Con el mínimo, la discrepancia queda visible y se investiga.
A13: Razón 3 | B13: Es el criterio con que un regulador o auditor evaluaría: la organización debe demostrar el control, no solo declararlo.
A14: Razón 4 | B14: Evita inflar la madurez, que es el sesgo natural de un assessment.
A15: REGLAS ADICIONALES
A16: Sin evidencia | B16: Si un control no tiene ninguna evidencia verificada, su puntaje máximo es 3 (Definido), porque no se puede demostrar que opera.
A17: N/A y vacíos | B17: Un N/A no cuenta como puntaje. Un control sin entrevistas queda en blanco y no pesa en el total.
A18: Discrepancia | B18: Si dos puntajes del mismo control difieren en 2 puntos o más, la columna Alerta marca 'Revisar'. Valide con el dueño del proceso antes de cerrar el control.
A19: Límite del método | B19: El mínimo puede ser severo si una entrevista está mal informada. Por eso la alerta exige validación. Una brecha identificada a tiempo es mejor que una madurez inflada.
A29: ID entrevista | B29: Fecha | C29: Dimensión (D1–D18) | D29: Área | E29: Cargo del entrevistado | F29: Control (ID) | G29: Lo que afirma el entrevistado | H29: Evidencia solicitada | I29: Evidencia verificada (Sí/No) | J29: Puntaje propuesto (1-5 / N/A) | K29: Observaciones / discrepancia | L29: Alerta (automática)
L30: =IF(F30="","",IF(COUNTIF($F$30:$F$229,F30)<2,"",IF(_xlfn.MAXIFS($J$30:$J$229,$F$30:$F$229,F30)-_xlfn.MINIFS($J$30:$J$229,$F$30:$F$229,F30)>=2,"Revisar: discrepancia","")))
L31: =IF(F31="","",IF(COUNTIF($F$30:$F$229,F31)<2,"",IF(_xlfn.MAXIFS($J$30:$J$229,$F$30:$F$229,F31)-_xlfn.MINIFS($J$30:$J$229,$F$30:$F$229,F31)>=2,"Revisar: discrepancia","")))
L32: =IF(F32="","",IF(COUNTIF($F$30:$F$229,F32)<2,"",IF(_xlfn.MAXIFS($J$30:$J$229,$F$30:$F$229,F32)-_xlfn.MINIFS($J$30:$J$229,$F$30:$F$229,F32)>=2,"Revisar: discrepancia","")))
L33: =IF(F33="","",IF(COUNTIF($F$30:$F$229,F33)<2,"",IF(_xlfn.MAXIFS($J$30:$J$229,$F$30:$F$229,F33)-_xlfn.MINIFS($J$30:$J$229,$F$30:$F$229,F33)>=2,"Revisar: discrepancia","")))
L34: =IF(F34="","",IF(COUNTIF($F$30:$F$229,F34)<2,"",IF(_xlfn.MAXIFS($J$30:$J$229,$F$30:$F$229,F34)-_xlfn.MINIFS($J$30:$J$229,$F$30:$F$229,F34)>=2,"Revisar: discrepancia","")))
L35: =IF(F35="","",IF(COUNTIF($F$30:$F$229,F35)<2,"",IF(_xlfn.MAXIFS($J$30:$J$229,$F$30:$F$229,F35)-_xlfn.MINIFS($J$30:$J$229,$F$30:$F$229,F35)>=2,"Revisar: discrepancia","")))
L36: =IF(F36="","",IF(COUNTIF($F$30:$F$229,F36)<2,"",IF(_xlfn.MAXIFS($J$30:$J$229,$F$30:$F$229,F36)-_xlfn.MINIFS($J$30:$J$229,$F$30:$F$229,F36)>=2,"Revisar: discrepancia","")))
L37: =IF(F37="","",IF(COUNTIF($F$30:$F$229,F37)<2,"",IF(_xlfn.MAXIFS($J$30:$J$229,$F$30:$F$229,F37)-_xlfn.MINIFS($J$30:$J$229,$F$30:$F$229,F37)>=2,"Revisar: discrepancia","")))
L38: =IF(F38="","",IF(COUNTIF($F$30:$F$229,F38)<2,"",IF(_xlfn.MAXIFS($J$30:$J$229,$F$30:$F$229,F38)-_xlfn.MINIFS($J$30:$J$229,$F$30:$F$229,F38)>=2,"Revisar: discrepancia","")))
L39: =IF(F39="","",IF(COUNTIF($F$30:$F$229,F39)<2,"",IF(_xlfn.MAXIFS($J$30:$J$229,$F$30:$F$229,F39)-_xlfn.MINIFS($J$30:$J$229,$F$30:$F$229,F39)>=2,"Revisar: discrepancia","")))
L40: =IF(F40="","",IF(COUNTIF($F$30:$F$229,F40)<2,"",IF(_xlfn.MAXIFS($J$30:$J$229,$F$30:$F$229,F40)-_xlfn.MINIFS($J$30:$J$229,$F$30:$F$229,F40)>=2,"Revisar: discrepancia","")))
L41: =IF(F41="","",IF(COUNTIF($F$30:$F$229,F41)<2,"",IF(_xlfn.MAXIFS($J$30:$J$229,$F$30:$F$229,F41)-_xlfn.MINIFS($J$30:$J$229,$F$30:$F$229,F41)>=2,"Revisar: discrepancia","")))
... L229: =IF(F229="","",IF(COUNTIF($F$30:$F$229,F229)<2,"",IF(_xlfn.MAXIFS($J$30:$J$229,$F$30:$F$229,F229)-_xlfn.MINIFS($J$30:$J$229,$F$30:$F$229,F229)>=2,"Revisar: discrepancia","")))

Sheet Dashboard
B1: DASHBOARD — CUMPLIMIENTO LEY 21.719
B2: ="Actualizado: "&TEXT(TODAY(),"dd/mm/yyyy")&" · Escala 1 (crítico) a 5 (optimizado)"
C4: Puntaje total ponderado (1-5) | D4: =Resumen!F28
C5: Nivel de madurez | D5: =IF(Resumen!E28/Resumen!D28<0.5,"Cobertura insuficiente (<50%)",Resumen!H28)
C6: Requisitos evaluados | D6: =Resumen!E28&" de "&Resumen!D28
C7: Controles puntuados | D7: =COUNTIF('Controles marcos'!E2:E172,">0")&" de 171"
C8: Solicitudes ARCOP vencidas | D8: =Resumen!C7
C9: Completitud del RAT (1-5) | D9: =Resumen!C4
C10: Requisitos incluidos en el puntaje | D10: =COUNTIF('Requisitos Ley'!K2:K199,"Sí")&" de "&COUNTA('Requisitos Ley'!B2:B199)
B11: Código | C11: Dimensión | D11: Puntaje (1-5) | E11: Nivel
B12: =Resumen!A10 | C12: =Resumen!B10 | D12: =Resumen!F10 | E12: =Resumen!H10
B13: =Resumen!A11 | C13: =Resumen!B11 | D13: =Resumen!F11 | E13: =Resumen!H11
B14: =Resumen!A12 | C14: =Resumen!B12 | D14: =Resumen!F12 | E14: =Resumen!H12
B15: =Resumen!A13 | C15: =Resumen!B13 | D15: =Resumen!F13 | E15: =Resumen!H13
B16: =Resumen!A14 | C16: =Resumen!B14 | D16: =Resumen!F14 | E16: =Resumen!H14
B17: =Resumen!A15 | C17: =Resumen!B15 | D17: =Resumen!F15 | E17: =Resumen!H15
B18: =Resumen!A16 | C18: =Resumen!B16 | D18: =Resumen!F16 | E18: =Resumen!H16
B19: =Resumen!A17 | C19: =Resumen!B17 | D19: =Resumen!F17 | E19: =Resumen!H17
B20: =Resumen!A18 | C20: =Resumen!B18 | D20: =Resumen!F18 | E20: =Resumen!H18
B21: =Resumen!A19 | C21: =Resumen!B19 | D21: =Resumen!F19 | E21: =Resumen!H19
B22: =Resumen!A20 | C22: =Resumen!B20 | D22: =Resumen!F20 | E22: =Resumen!H20
B23: =Resumen!A21 | C23: =Resumen!B21 | D23: =Resumen!F21 | E23: =Resumen!H21
... B29: =Resumen!A27 | C29: =Resumen!B27 | D29: =Resumen!F27 | E29: =Resumen!H27
C31: Marco de referencia | D31: Evaluados | E31: Puntaje (1-5)
C32: =Resumen!A33 | D32: =Resumen!D33 | E32: =Resumen!E33
C33: =Resumen!A34 | D33: =Resumen!D34 | E33: =Resumen!E34
C34: =Resumen!A35 | D34: =Resumen!D35 | E34: =Resumen!E35
C35: =Resumen!A36 | D35: =Resumen!D36 | E35: =Resumen!E36
C36: =Resumen!A37 | D36: =Resumen!D37 | E36: =Resumen!E37
C37: =Resumen!A38 | D37: =Resumen!D38 | E37: =Resumen!E38
B39: Código | C39: Brecha prioritaria (menor puntaje evaluado) | D39: Puntaje (1-5)
B40: =IF(D40="","",INDEX('Requisitos Ley'!$B$2:$B$199,MATCH(D40,'Requisitos Ley'!$L$2:$L$199,0))) | C40: =IF(D40="","",INDEX('Requisitos Ley'!$C$2:$C$199,MATCH(D40,'Requisitos Ley'!$L$2:$L$199,0))) | D40: =IFERROR(SMALL('Requisitos Ley'!$L$2:$L$199,1),"")
B41: =IF(D41="","",INDEX('Requisitos Ley'!$B$2:$B$199,MATCH(D41,'Requisitos Ley'!$L$2:$L$199,0))) | C41: =IF(D41="","",INDEX('Requisitos Ley'!$C$2:$C$199,MATCH(D41,'Requisitos Ley'!$L$2:$L$199,0))) | D41: =IFERROR(SMALL('Requisitos Ley'!$L$2:$L$199,2),"")
B42: =IF(D42="","",INDEX('Requisitos Ley'!$B$2:$B$199,MATCH(D42,'Requisitos Ley'!$L$2:$L$199,0))) | C42: =IF(D42="","",INDEX('Requisitos Ley'!$C$2:$C$199,MATCH(D42,'Requisitos Ley'!$L$2:$L$199,0))) | D42: =IFERROR(SMALL('Requisitos Ley'!$L$2:$L$199,3),"")
B43: =IF(D43="","",INDEX('Requisitos Ley'!$B$2:$B$199,MATCH(D43,'Requisitos Ley'!$L$2:$L$199,0))) | C43: =IF(D43="","",INDEX('Requisitos Ley'!$C$2:$C$199,MATCH(D43,'Requisitos Ley'!$L$2:$L$199,0))) | D43: =IFERROR(SMALL('Requisitos Ley'!$L$2:$L$199,4),"")
B44: =IF(D44="","",INDEX('Requisitos Ley'!$B$2:$B$199,MATCH(D44,'Requisitos Ley'!$L$2:$L$199,0))) | C44: =IF(D44="","",INDEX('Requisitos Ley'!$C$2:$C$199,MATCH(D44,'Requisitos Ley'!$L$2:$L$199,0))) | D44: =IFERROR(SMALL('Requisitos Ley'!$L$2:$L$199,5),"")

Sheet Resumen
A1: RESUMEN INTEGRADO — LEY 21.719
A3: INDICADORES DERIVADOS DEL LEVANTAMIENTO (escala 1–5)
A4: Completitud del RAT (campos obligatorios por actividad) | C4: =IFERROR(1+4*AVERAGE(RAT!$AA$2:$AA$60),"")
A5: Derechos ARCOP atendidos en plazo | C5: =IFERROR(1+4*(COUNTIF(ARCOP!I:I,"A tiempo")+COUNTIF(ARCOP!I:I,"En plazo"))/COUNTIF(ARCOP!A:A,"ARC-*"),"")
A6: Transferencias con garantía definida | C6: =IFERROR(1+4*COUNTIF(Transferencias!J:J,"Sí")/COUNTIF(Transferencias!A:A,"RAT-*"),"")
A7: Solicitudes ARCOP vencidas (informativo, no suma al puntaje) | C7: =COUNTIF(ARCOP!I:I,"Vencida")
A9: Código | B9: Dimensión | C9: Peso | D9: Requisitos | E9: Evaluados | F9: Puntaje (1-5) | G9: % cumplimiento | H9: Nivel
A10: D1 | B10: Gobierno y responsabilidad proactiva | C10: 0.08 | D10: =COUNTIFS('Requisitos Ley'!$A$2:$A$199,A10,'Requisitos Ley'!$K$2:$K$199,"Sí") | E10: =COUNTIFS('Requisitos Ley'!$A$2:$A$199,A10,'Requisitos Ley'!$L$2:$L$199,">0") | F10: =IFERROR(AVERAGEIFS('Requisitos Ley'!$L$2:$L$199,'Requisitos Ley'!$A$2:$A$199,A10),0) | G10: =IF(F10>0,F10/5,"") | H10: =IF(F10=0,"Sin evaluar",IF(F10<2,"Crítico",IF(F10<3,"Inicial",IF(F10<4,"En desarrollo",IF(F10<4.6,"Avanzado","Optimizado")))))
A11: D2 | B11: Inventario y Registro de Actividades de Tratamiento (RAT) | C11: 0.06 | D11: =COUNTIFS('Requisitos Ley'!$A$2:$A$199,A11,'Requisitos Ley'!$K$2:$K$199,"Sí") | E11: =COUNTIFS('Requisitos Ley'!$A$2:$A$199,A11,'Requisitos Ley'!$L$2:$L$199,">0") | F11: =IFERROR(AVERAGEIFS('Requisitos Ley'!$L$2:$L$199,'Requisitos Ley'!$A$2:$A$199,A11),0) | G11: =IF(F11>0,F11/5,"") | H11: =IF(F11=0,"Sin evaluar",IF(F11<2,"Crítico",IF(F11<3,"Inicial",IF(F11<4,"En desarrollo",IF(F11<4.6,"Avanzado","Optimizado")))))
A12: D3 | B12: Licitud del tratamiento y consentimiento | C12: 0.06 | D12: =COUNTIFS('Requisitos Ley'!$A$2:$A$199,A12,'Requisitos Ley'!$K$2:$K$199,"Sí") | E12: =COUNTIFS('Requisitos Ley'!$A$2:$A$199,A12,'Requisitos Ley'!$L$2:$L$199,">0") | F12: =IFERROR(AVERAGEIFS('Requisitos Ley'!$L$2:$L$199,'Requisitos Ley'!$A$2:$A$199,A12),0) | G12: =IF(F12>0,F12/5,"") | H12: =IF(F12=0,"Sin evaluar",IF(F12<2,"Crítico",IF(F12<3,"Inicial",IF(F12<4,"En desarrollo",IF(F12<4.6,"Avanzado","Optimizado")))))
A13: D4 | B13: Derechos de los titulares (ARCOP) | C13: 0.06 | D13: =COUNTIFS('Requisitos Ley'!$A$2:$A$199,A13,'Requisitos Ley'!$K$2:$K$199,"Sí") | E13: =COUNTIFS('Requisitos Ley'!$A$2:$A$199,A13,'Requisitos Ley'!$L$2:$L$199,">0") | F13: =IFERROR(AVERAGEIFS('Requisitos Ley'!$L$2:$L$199,'Requisitos Ley'!$A$2:$A$199,A13),0) | G13: =IF(F13>0,F13/5,"") | H13: =IF(F13=0,"Sin evaluar",IF(F13<2,"Crítico",IF(F13<3,"Inicial",IF(F13<4,"En desarrollo",IF(F13<4.6,"Avanzado","Optimizado")))))
A14: D5 | B14: Principios y ciclo de vida del dato | C14: 0.05 | D14: =COUNTIFS('Requisitos Ley'!$A$2:$A$199,A14,'Requisitos Ley'!$K$2:$K$199,"Sí") | E14: =COUNTIFS('Requisitos Ley'!$A$2:$A$199,A14,'Requisitos Ley'!$L$2:$L$199,">0") | F14: =IFERROR(AVERAGEIFS('Requisitos Ley'!$L$2:$L$199,'Requisitos Ley'!$A$2:$A$199,A14),0) | G14: =IF(F14>0,F14/5,"") | H14: =IF(F14=0,"Sin evaluar",IF(F14<2,"Crítico",IF(F14<3,"Inicial",IF(F14<4,"En desarrollo",IF(F14<4.6,"Avanzado","Optimizado")))))
A15: D6 | B15: Datos sensibles, biométricos y de menores | C15: 0.05 | D15: =COUNTIFS('Requisitos Ley'!$A$2:$A$199,A15,'Requisitos Ley'!$K$2:$K$199,"Sí") | E15: =COUNTIFS('Requisitos Ley'!$A$2:$A$199,A15,'Requisitos Ley'!$L$2:$L$199,">0") | F15: =IFERROR(AVERAGEIFS('Requisitos Ley'!$L$2:$L$199,'Requisitos Ley'!$A$2:$A$199,A15),0) | G15: =IF(F15>0,F15/5,"") | H15: =IF(F15=0,"Sin evaluar",IF(F15<2,"Crítico",IF(F15<3,"Inicial",IF(F15<4,"En desarrollo",IF(F15<4.6,"Avanzado","Optimizado")))))
A16: D7 | B16: Evaluación de impacto y privacidad desde el diseño | C16: 0.04 | D16: =COUNTIFS('Requisitos Ley'!$A$2:$A$199,A16,'Requisitos Ley'!$K$2:$K$199,"Sí") | E16: =COUNTIFS('Requisitos Ley'!$A$2:$A$199,A16,'Requisitos Ley'!$L$2:$L$199,">0") | F16: =IFERROR(AVERAGEIFS('Requisitos Ley'!$L$2:$L$199,'Requisitos Ley'!$A$2:$A$199,A16),0) | G16: =IF(F16>0,F16/5,"") | H16: =IF(F16=0,"Sin evaluar",IF(F16<2,"Crítico",IF(F16<3,"Inicial",IF(F16<4,"En desarrollo",IF(F16<4.6,"Avanzado","Optimizado")))))
A17: D8 | B17: Seguridad de la información (RBAC, malware, MFA) | C17: 0.11 | D17: =COUNTIFS('Requisitos Ley'!$A$2:$A$199,A17,'Requisitos Ley'!$K$2:$K$199,"Sí") | E17: =COUNTIFS('Requisitos Ley'!$A$2:$A$199,A17,'Requisitos Ley'!$L$2:$L$199,">0") | F17: =IFERROR(AVERAGEIFS('Requisitos Ley'!$L$2:$L$199,'Requisitos Ley'!$A$2:$A$199,A17),0) | G17: =IF(F17>0,F17/5,"") | H17: =IF(F17=0,"Sin evaluar",IF(F17<2,"Crítico",IF(F17<3,"Inicial",IF(F17<4,"En desarrollo",IF(F17<4.6,"Avanzado","Optimizado")))))
A18: D9 | B18: Gestión de incidentes, continuidad y DRP | C18: 0.07 | D18: =COUNTIFS('Requisitos Ley'!$A$2:$A$199,A18,'Requisitos Ley'!$K$2:$K$199,"Sí") | E18: =COUNTIFS('Requisitos Ley'!$A$2:$A$199,A18,'Requisitos Ley'!$L$2:$L$199,">0") | F18: =IFERROR(AVERAGEIFS('Requisitos Ley'!$L$2:$L$199,'Requisitos Ley'!$A$2:$A$199,A18),0) | G18: =IF(F18>0,F18/5,"") | H18: =IF(F18=0,"Sin evaluar",IF(F18<2,"Crítico",IF(F18<3,"Inicial",IF(F18<4,"En desarrollo",IF(F18<4.6,"Avanzado","Optimizado")))))
A19: D10 | B19: Encargados, proveedores y transferencias internacionales | C19: 0.05 | D19: =COUNTIFS('Requisitos Ley'!$A$2:$A$199,A19,'Requisitos Ley'!$K$2:$K$199,"Sí") | E19: =COUNTIFS('Requisitos Ley'!$A$2:$A$199,A19,'Requisitos Ley'!$L$2:$L$199,">0") | F19: =IFERROR(AVERAGEIFS('Requisitos Ley'!$L$2:$L$199,'Requisitos Ley'!$A$2:$A$199,A19),0) | G19: =IF(F19>0,F19/5,"") | H19: =IF(F19=0,"Sin evaluar",IF(F19<2,"Crítico",IF(F19<3,"Inicial",IF(F19<4,"En desarrollo",IF(F19<4.6,"Avanzado","Optimizado")))))
A20: D11 | B20: Capacitación, cultura y phishing | C20: 0.04 | D20: =COUNTIFS('Requisitos Ley'!$A$2:$A$199,A20,'Requisitos Ley'!$K$2:$K$199,"Sí") | E20: =COUNTIFS('Requisitos Ley'!$A$2:$A$199,A20,'Requisitos Ley'!$L$2:$L$199,">0") | F20: =IFERROR(AVERAGEIFS('Requisitos Ley'!$L$2:$L$199,'Requisitos Ley'!$A$2:$A$199,A20),0) | G20: =IF(F20>0,F20/5,"") | H20: =IF(F20=0,"Sin evaluar",IF(F20<2,"Crítico",IF(F20<3,"Inicial",IF(F20<4,"En desarrollo",IF(F20<4.6,"Avanzado","Optimizado")))))
A21: D12 | B21: Auditoría, monitoreo y mejora continua | C21: 0.03 | D21: =COUNTIFS('Requisitos Ley'!$A$2:$A$199,A21,'Requisitos Ley'!$K$2:$K$199,"Sí") | E21: =COUNTIFS('Requisitos Ley'!$A$2:$A$199,A21,'Requisitos Ley'!$L$2:$L$199,">0") | F21: =IFERROR(AVERAGEIFS('Requisitos Ley'!$L$2:$L$199,'Requisitos Ley'!$A$2:$A$199,A21),0) | G21: =IF(F21>0,F21/5,"") | H21: =IF(F21=0,"Sin evaluar",IF(F21<2,"Crítico",IF(F21<3,"Inicial",IF(F21<4,"En desarrollo",IF(F21<4.6,"Avanzado","Optimizado")))))
... A27: D18 | B27: Clientes, leads, prospectos y marketing | C27: 0.05 | D27: =COUNTIFS('Requisitos Ley'!$A$2:$A$199,A27,'Requisitos Ley'!$K$2:$K$199,"Sí") | E27: =COUNTIFS('Requisitos Ley'!$A$2:$A$199,A27,'Requisitos Ley'!$L$2:$L$199,">0") | F27: =IFERROR(AVERAGEIFS('Requisitos Ley'!$L$2:$L$199,'Requisitos Ley'!$A$2:$A$199,A27),0) | G27: =IF(F27>0,F27/5,"") | H27: =IF(F27=0,"Sin evaluar",IF(F27<2,"Crítico",IF(F27<3,"Inicial",IF(F27<4,"En desarrollo",IF(F27<4.6,"Avanzado","Optimizado")))))
A28: TOTAL | B28: Puntaje total ponderado (solo dimensiones evaluadas) | C28: =SUM(C10:C27) | D28: =SUM(D10:D27) | E28: =SUM(E10:E27) | F28: =IFERROR(SUMPRODUCT((F10:F27>0)*F10:F27*C10:C27)/SUMPRODUCT((F10:F27>0)*C10:C27),0) | G28: =IF(F28>0,F28/5,"") | H28: =IF(F28=0,"Sin evaluar",IF(F28<2,"Crítico",IF(F28<3,"Inicial",IF(F28<4,"En desarrollo",IF(F28<4.6,"Avanzado","Optimizado")))))
A29: =IF(ROUND(C28,4)=1,"Pesos correctos (100%)","ATENCIÓN: los pesos no suman 100%")
A31: VISTA POR MARCO DE REFERENCIA (promedio de controles puntuados)
A32: Marco | C32: Controles | D32: Evaluados | E32: Puntaje (1-5)
A33: ISO 27001:2022 | C33: =COUNTIF('Controles marcos'!$A$2:$A$172,A33) | D33: =COUNTIFS('Controles marcos'!$A$2:$A$172,A33,'Controles marcos'!$E$2:$E$172,">0") | E33: =IFERROR(AVERAGEIFS('Controles marcos'!$E$2:$E$172,'Controles marcos'!$A$2:$A$172,A33),"")
A34: NIST CSF 2.0 | C34: =COUNTIF('Controles marcos'!$A$2:$A$172,A34) | D34: =COUNTIFS('Controles marcos'!$A$2:$A$172,A34,'Controles marcos'!$E$2:$E$172,">0") | E34: =IFERROR(AVERAGEIFS('Controles marcos'!$E$2:$E$172,'Controles marcos'!$A$2:$A$172,A34),"")
A35: CIS Controls v8.1 | C35: =COUNTIF('Controles marcos'!$A$2:$A$172,A35) | D35: =COUNTIFS('Controles marcos'!$A$2:$A$172,A35,'Controles marcos'!$E$2:$E$172,">0") | E35: =IFERROR(AVERAGEIFS('Controles marcos'!$E$2:$E$172,'Controles marcos'!$A$2:$A$172,A35),"")
A36: COBIT 5 | C36: =COUNTIF('Controles marcos'!$A$2:$A$172,A36) | D36: =COUNTIFS('Controles marcos'!$A$2:$A$172,A36,'Controles marcos'!$E$2:$E$172,">0") | E36: =IFERROR(AVERAGEIFS('Controles marcos'!$E$2:$E$172,'Controles marcos'!$A$2:$A$172,A36),"")
A37: PCI DSS v4.0.1 | C37: =COUNTIF('Controles marcos'!$A$2:$A$172,A37) | D37: =COUNTIFS('Controles marcos'!$A$2:$A$172,A37,'Controles marcos'!$E$2:$E$172,">0") | E37: =IFERROR(AVERAGEIFS('Controles marcos'!$E$2:$E$172,'Controles marcos'!$A$2:$A$172,A37),"")
A38: Normativa chilena | C38: =COUNTIF('Controles marcos'!$A$2:$A$172,A38) | D38: =COUNTIFS('Controles marcos'!$A$2:$A$172,A38,'Controles marcos'!$E$2:$E$172,">0") | E38: =IFERROR(AVERAGEIFS('Controles marcos'!$E$2:$E$172,'Controles marcos'!$A$2:$A$172,A38),"")
A40: ISO 27001 por tema
A42: NIST CSF 2.0 por función
A43: GOVERN | C43: =COUNTIFS('Controles marcos'!$D$2:$D$172,A43,'Controles marcos'!$A$2:$A$172,"NIST CSF 2.0") | D43: =COUNTIFS('Controles marcos'!$D$2:$D$172,A43,'Controles marcos'!$A$2:$A$172,"NIST CSF 2.0",'Controles marcos'!$E$2:$E$172,">0") | E43: =IFERROR(AVERAGEIFS('Controles marcos'!$E$2:$E$172,'Controles marcos'!$D$2:$D$172,A43,'Controles marcos'!$A$2:$A$172,"NIST CSF 2.0"),"")
A44: IDENTIFY | C44: =COUNTIFS('Controles marcos'!$D$2:$D$172,A44,'Controles marcos'!$A$2:$A$172,"NIST CSF 2.0") | D44: =COUNTIFS('Controles marcos'!$D$2:$D$172,A44,'Controles marcos'!$A$2:$A$172,"NIST CSF 2.0",'Controles marcos'!$E$2:$E$172,">0") | E44: =IFERROR(AVERAGEIFS('Controles marcos'!$E$2:$E$172,'Controles marcos'!$D$2:$D$172,A44,'Controles marcos'!$A$2:$A$172,"NIST CSF 2.0"),"")
A45: PROTECT | C45: =COUNTIFS('Controles marcos'!$D$2:$D$172,A45,'Controles marcos'!$A$2:$A$172,"NIST CSF 2.0") | D45: =COUNTIFS('Controles marcos'!$D$2:$D$172,A45,'Controles marcos'!$A$2:$A$172,"NIST CSF 2.0",'Controles marcos'!$E$2:$E$172,">0") | E45: =IFERROR(AVERAGEIFS('Controles marcos'!$E$2:$E$172,'Controles marcos'!$D$2:$D$172,A45,'Controles marcos'!$A$2:$A$172,"NIST CSF 2.0"),"")
A46: RESPOND | C46: =COUNTIFS('Controles marcos'!$D$2:$D$172,A46,'Controles marcos'!$A$2:$A$172,"NIST CSF 2.0") | D46: =COUNTIFS('Controles marcos'!$D$2:$D$172,A46,'Controles marcos'!$A$2:$A$172,"NIST CSF 2.0",'Controles marcos'!$E$2:$E$172,">0") | E46: =IFERROR(AVERAGEIFS('Controles marcos'!$E$2:$E$172,'Controles marcos'!$D$2:$D$172,A46,'Controles marcos'!$A$2:$A$172,"NIST CSF 2.0"),"")
A47: RECOVER | C47: =COUNTIFS('Controles marcos'!$D$2:$D$172,A47,'Controles marcos'!$A$2:$A$172,"NIST CSF 2.0") | D47: =COUNTIFS('Controles marcos'!$D$2:$D$172,A47,'Controles marcos'!$A$2:$A$172,"NIST CSF 2.0",'Controles marcos'!$E$2:$E$172,">0") | E47: =IFERROR(AVERAGEIFS('Controles marcos'!$E$2:$E$172,'Controles marcos'!$D$2:$D$172,A47,'Controles marcos'!$A$2:$A$172,"NIST CSF 2.0"),"")

Sheet Requisitos Ley
A1: Dimensión | B1: ID | C1: Requisito: qué debe existir y cómo verificarlo | D1: Controles e indicadores que alimentan el puntaje (el puntaje es su promedio) | E1: Puntaje (1-5) | F1: Evidencia encontrada (escriba aquí) | G1: Brecha / plan de acción (escriba aquí) | H1: Responsable | I1: Fecha límite | J1: Tipo de requisito | K1: Incluir en puntaje (Sí/No) | L1: Puntaje considerado (automático)
A2: D1 | B2: 1.1 | C2: La organización tiene una política de protección de datos personales aprobada por la dirección y comunicada a todo el personal. Verificar: documento firmado, fecha de aprobación y constancia de difusión. | D2: • 5.1 · Políticas de seguridad de la información • NIST GV.PO-01 · Política de gestión del riesgo establecida | E2: =IFERROR(AVERAGE('Controles marcos'!$E$2,'Controles marcos'!$E$104),"") | J2: Obligatorio Ley 21.719 | K2: Sí | L2: =IF(AND(K2="Sí",ISNUMBER(E2)),E2,"")
A3: D1 | B3: 1.2 | C3: Existe una persona designada formalmente como responsable de privacidad (DPO o equivalente), con funciones y autoridad escritas. Verificar: nombramiento, descripción de funciones y a quién reporta. | D3: • 5.2 · Roles y responsabilidades de SI • 5.3 · Segregación de funciones • NIST GV.RR-02 · Roles, responsabilidades y autoridades definidos • L21.719 Art.50 · Atribuciones del delegado de protección de datos • L20.393 Art.4 N3 · Encargado de prevención de delitos | E3: =IFERROR(AVERAGE('Controles marcos'!$E$3,'Controles marcos'!$E$4,'Controles marcos'!$E$101,'Controles marcos'!$E$164,'Controles marcos'!$E$169),"") | J3: Obligatorio Ley 21.719 | K3: Sí | L3: =IF(AND(K3="Sí",ISNUMBER(E3)),E3,"")
A4: D1 | B4: 1.3 | C4: La dirección asigna personas, herramientas y presupuesto para cumplir la ley. Verificar: presupuesto anual de privacidad y dedicación del responsable. | D4: • 5.4 · Responsabilidades de la dirección • NIST GV.RR-03 · Recursos asignados a la ciberseguridad | E4: =IFERROR(AVERAGE('Controles marcos'!$E$5,'Controles marcos'!$E$102),"") | J4: Obligatorio Ley 21.719 | K4: Sí | L4: =IF(AND(K4="Sí",ISNUMBER(E4)),E4,"")
A5: D1 | B5: 1.4 | C5: Existe un programa de adecuación a la ley con modelo de prevención de infracciones documentado. Verificar: plan con responsables, fechas y avance. | D5: • 5.31 · Requisitos legales, estatutarios y contractuales • 5.36 · Cumplimiento con políticas y normas de SI • NIST GV.OC-03 · Obligaciones legales, regulatorias y contractuales • L21.719 Programa adecuación · Programa de adecuación de la organización • L20.393 Art.4 · Modelo de prevención de delitos vigente • L21.719 Art.49 · Modelo de prevención de infracciones • L20.393 Art.4 N2 · Protocolos y procedimientos de control | E5: =IFERROR(AVERAGE('Controles marcos'!$E$32,'Controles marcos'!$E$37,'Controles marcos'!$E$97,'Controles marcos'!$E$165,'Controles marcos'!$E$168,'Controles marcos'!$E$163,'Controles marcos'!$E$170),"") | J5: Obligatorio Ley 21.719 | K5: Sí | L5: =IF(AND(K5="Sí",ISNUMBER(E5)),E5,"")
A6: D1 | B6: 1.5 | C6: Las evidencias de cumplimiento están ordenadas y se pueden presentar a la autoridad en cualquier momento. Verificar: carpeta de evidencias actualizada y con fechas. | D6: • 5.36 · Cumplimiento con políticas y normas de SI • 5.35 · Revisión independiente de SI • NIST GV.PO-02 · Política revisada y actualizada | E6: =IFERROR(AVERAGE('Controles marcos'!$E$37,'Controles marcos'!$E$36,'Controles marcos'!$E$105),"") | J6: Obligatorio Ley 21.719 | K6: Sí | L6: =IF(AND(K6="Sí",ISNUMBER(E6)),E6,"")
A7: D1 | B7: 1.6 | C7: Para cada tratamiento está definido si la organización actúa como responsable (decide para qué se usan los datos) o encargado (los trata por cuenta de otro). Verificar: matriz de roles por tratamiento. | D7: • 5.31 · Requisitos legales, estatutarios y contractuales • NIST GV.OC-02 · Partes interesadas y sus expectativas | E7: =IFERROR(AVERAGE('Controles marcos'!$E$32,'Controles marcos'!$E$96),"") | J7: Obligatorio Ley 21.719 | K7: Sí | L7: =IF(AND(K7="Sí",ISNUMBER(E7)),E7,"")
A8: D1 | B8: 1.7 | C8: Existen contactos formales con la Agencia de Protección de Datos, el CPLT y la ANCI, y se mantienen actualizados. Verificar: directorio de contactos y fecha de la última actualización. | D8: • 5.5 · Contacto con autoridades • 5.6 · Contacto con grupos de interés especial | E8: =IFERROR(AVERAGE('Controles marcos'!$E$6,'Controles marcos'!$E$7),"") | J8: Obligatorio Ley 21.719 | K8: Sí | L8: =IF(AND(K8="Sí",ISNUMBER(E8)),E8,"")
A9: D1 | B9: 1.8 | C9: La dirección lidera la cultura de cumplimiento y el riesgo de privacidad forma parte de sus decisiones. Verificar: actas o reportes donde la dirección revisa privacidad. | D9: • NIST GV.RR-01 · Liderazgo responsable del riesgo de ciberseguridad • NIST GV.OC-01 · Misión y contexto de la organización | E9: =IFERROR(AVERAGE('Controles marcos'!$E$100,'Controles marcos'!$E$95),"") | J9: Obligatorio Ley 21.719 | K9: Sí | L9: =IF(AND(K9="Sí",ISNUMBER(E9)),E9,"")
A10: D1 | B10: 1.9 | C10: Clientes, proveedores y otras partes externas conocen el compromiso de la organización con la privacidad y la seguridad. Verificar: políticas publicadas y declaraciones en contratos o sitio web. | D10: • NIST GV.OC-04 · Expectativas de partes externas sobre la organización • NIST GV.OC-05 · Dependencias y servicios críticos de la organización | E10: =IFERROR(AVERAGE('Controles marcos'!$E$98,'Controles marcos'!$E$99),"") | J10: Obligatorio Ley 21.719 | K10: Sí | L10: =IF(AND(K10="Sí",ISNUMBER(E10)),E10,"")
A11: D1 | B11: 1.10 | C11: Los procedimientos para tratar datos personales están escritos y disponibles para quien los usa. Verificar: lista de procedimientos con versión y fecha. | D11: • 5.37 · Procedimientos de operación documentados | E11: =IFERROR(AVERAGE('Controles marcos'!$E$38),"") | J11: Obligatorio Ley 21.719 | K11: Sí | L11: =IF(AND(K11="Sí",ISNUMBER(E11)),E11,"")
A12: D1 | B12: 1.11 | C12: Los sistemas que tratan datos cuentan con licencias vigentes y se controla el uso de software con propiedad intelectual. Verificar: inventario de licencias. | D12: • 5.32 · Derechos de propiedad intelectual | E12: =IFERROR(AVERAGE('Controles marcos'!$E$33),"") | J12: Obligatorio Ley 21.719 | K12: Sí | L12: =IF(AND(K12="Sí",ISNUMBER(E12)),E12,"")
A13: D1 | B13: 1.12 | C13: Existen políticas técnicas escritas y aprobadas sobre control de acceso por roles, respaldos, malware, phishing y uso aceptable. Verificar: cada política, su fecha y quién la aprueba. | D13: • 5.10 · Uso aceptable de información • 5.1 · Políticas de seguridad de la información • NIST GV.PO-01 · Política de gestión del riesgo establecida | E13: =IFERROR(AVERAGE('Controles marcos'!$E$11,'Controles marcos'!$E$2,'Controles marcos'!$E$104),"") | J13: Obligatorio Ley 21.719 | K13: Sí | L13: =IF(AND(K13="Sí",ISNUMBER(E13)),E13,"")
A14: D1 | B14: 1.13 | C14: Comité de privacidad formal con actas que revisa tratamientos de alto riesgo y decisiones de cumplimiento. | D14: • 5.4 · Responsabilidades de la dirección • NIST GV.RR-01 · Liderazgo responsable del riesgo de ciberseguridad | E14: =IFERROR(AVERAGE('Controles marcos'!$E$5,'Controles marcos'!$E$100),"") | J14: Extra (marco o buena práctica) | K14: No | L14: =IF(AND(K14="Sí",ISNUMBER(E14)),E14,"")
A15: D1 | B15: 1.14 | C15: Evaluación de privacidad y seguridad antes de contratar proveedores tecnológicos nuevos (due diligence). | D15: • 5.19 · Seguridad en relaciones con proveedores • 5.21 · Gestión de seguridad en cadena TIC | E15: =IFERROR(AVERAGE('Controles marcos'!$E$20,'Controles marcos'!$E$22),"") | J15: Extra (marco o buena práctica) | K15: No | L15: =IF(AND(K15="Sí",ISNUMBER(E15)),E15,"")
A16: D2 | B16: 2.1 | C16: Existe un Registro de Actividades de Tratamiento (RAT) que describe, para cada actividad, la finalidad, la base legal, los tipos de datos, los titulares, los destinatarios, los plazos y las medidas de seguridad. Verificar: hoja RAT completa (indicador automático). | D16: • Indicador automático: completitud del RAT (hoja RAT) • 5.9 · Inventario de información y activos | E16: =IFERROR(AVERAGE(Resumen!$C$4,'Controles marcos'!$E$10),"") | J16: Obligatorio Ley 21.719 | K16: Sí | L16: =IF(AND(K16="Sí",ISNUMBER(E16)),E16,"")
A17: D2 | B17: 2.2 | C17: Existe un listado de los sistemas, aplicaciones y bases de datos que tratan datos personales. Verificar: inventario con nombre del sistema, dueño y tipo de datos. | D17: • 5.9 · Inventario de información y activos • NIST ID.AM-02 · Inventario de software y servicios • CIS 1 · Inventario de activos empresariales | E17: =IFERROR(AVERAGE('Controles marcos'!$E$10,'Controles marcos'!$E$107,'Controles marcos'!$E$137),"") | J17: Obligatorio Ley 21.719 | K17: Sí | L17: =IF(AND(K17="Sí",ISNUMBER(E17)),E17,"")
A18: D2 | B18: 2.3 | C18: Hay un diagrama de los flujos de datos personales dentro de la organización y hacia terceros (incluida la nube). Verificar: diagrama actualizado y su fecha. | D18: • NIST ID.AM-03 · Mapa de flujos de datos y comunicaciones | E18: =IFERROR(AVERAGE('Controles marcos'!$E$108),"") | J18: Obligatorio Ley 21.719 | K18: Sí | L18: =IF(AND(K18="Sí",ISNUMBER(E18)),E18,"")
A19: D2 | B19: 2.4 | C19: El RAT se revisa al menos una vez al año y cada vez que cambia un proceso o sistema. Verificar: fecha de última revisión en la hoja RAT y registro de cambios. | D19: • NIST ID.AM-01 · Inventario de hardware • 5.9 · Inventario de información y activos | E19: =IFERROR(AVERAGE('Controles marcos'!$E$106,'Controles marcos'!$E$10),"") | J19: Obligatorio Ley 21.719 | K19: Sí | L19: =IF(AND(K19="Sí",ISNUMBER(E19)),E19,"")
A20: D2 | B20: 2.5 | C20: Los tratamientos de alto riesgo (por ejemplo, datos sensibles a gran escala, biometría o videovigilancia) están identificados en el RAT. Verificar: marca de riesgo en cada actividad. | D20: • NIST ID.AM-05 · Priorización de activos por criticidad | E20: =IFERROR(AVERAGE('Controles marcos'!$E$109),"") | J20: Obligatorio Ley 21.719 | K20: Sí | L20: =IF(AND(K20="Sí",ISNUMBER(E20)),E20,"")
A21: D2 | B21: 2.6 | C21: Los datos personales están clasificados y etiquetados según su sensibilidad en repositorios y documentos. Verificar: esquema de clasificación y ejemplos etiquetados. | D21: • 5.12 · Clasificación de la información • 5.13 · Etiquetado de la información | E21: =IFERROR(AVERAGE('Controles marcos'!$E$13,'Controles marcos'!$E$14),"") | J21: Obligatorio Ley 21.719 | K21: Sí | L21: =IF(AND(K21="Sí",ISNUMBER(E21)),E21,"")
A22: D2 | B22: 2.7 | C22: Los sistemas y datos se gestionan desde su adquisición hasta su baja, con responsable en cada etapa. Verificar: procedimiento de ciclo de vida. | D22: • NIST ID.AM-08 · Gestión de activos a lo largo de su ciclo de vida | E22: =IFERROR(AVERAGE('Controles marcos'!$E$110),"") | J22: Obligatorio Ley 21.719 | K22: Sí | L22: =IF(AND(K22="Sí",ISNUMBER(E22)),E22,"")
A23: D3 | B23: 3.1 | C23: Cada tratamiento de datos personales tiene una base legal (consentimiento, contrato, obligación legal, interés legítimo u otra) definida antes de iniciarse. Verificar: base legal registrada en el RAT. | D23: • 5.34 · Privacidad y protección de datos personales | E23: =IFERROR(AVERAGE('Controles marcos'!$E$35),"") | J23: Obligatorio Ley 21.719 | K23: Sí | L23: =IF(AND(K23="Sí",ISNUMBER(E23)),E23,"")
A24: D3 | B24: 3.2 | C24: El consentimiento es libre, informado, específico e inequívoco, y no hay casillas premarcadas. Verificar: formularios reales con su captura de pantalla. | D24: • 5.34 · Privacidad y protección de datos personales | E24: =IFERROR(AVERAGE('Controles marcos'!$E$35),"") | J24: Obligatorio Ley 21.719 | K24: Sí | L24: =IF(AND(K24="Sí",ISNUMBER(E24)),E24,"")
A25: D3 | B25: 3.3 | C25: Cada consentimiento queda registrado con fecha, canal, versión del aviso y la finalidad aceptada. Verificar: muestra de registros de consentimiento. | D25: • 5.34 · Privacidad y protección de datos personales • 5.33 · Protección de registros | E25: =IFERROR(AVERAGE('Controles marcos'!$E$35,'Controles marcos'!$E$34),"") | J25: Obligatorio Ley 21.719 | K25: Sí | L25: =IF(AND(K25="Sí",ISNUMBER(E25)),E25,"")
A26: D3 | B26: 3.4 | C26: El titular puede revocar su consentimiento con la misma facilidad con que lo otorgó. Verificar: prueba del proceso de revocación (cuántos pasos y en qué canal). | D26: • 5.34 · Privacidad y protección de datos personales | E26: =IFERROR(AVERAGE('Controles marcos'!$E$35),"") | J26: Obligatorio Ley 21.719 | K26: Sí | L26: =IF(AND(K26="Sí",ISNUMBER(E26)),E26,"")
A27: D3 | B27: 3.5 | C27: Cuando la base legal es interés legítimo, existe una evaluación escrita que pondera ese interés frente a los derechos del titular. Verificar: documento de ponderación por tratamiento. | D27: • 5.34 · Privacidad y protección de datos personales | E27: =IFERROR(AVERAGE('Controles marcos'!$E$35),"") | J27: Obligatorio Ley 21.719 | K27: Sí | L27: =IF(AND(K27="Sí",ISNUMBER(E27)),E27,"")
A28: D3 | B28: 3.6 | C28: Al recolectar datos se entrega al titular el aviso de privacidad completo (quién trata, para qué, base legal, derechos y plazos). Verificar: aviso publicado y se muestra en cada punto de captura. | D28: • 5.34 · Privacidad y protección de datos personales | E28: =IFERROR(AVERAGE('Controles marcos'!$E$35),"") | J28: Obligatorio Ley 21.719 | K28: Sí | L28: =IF(AND(K28="Sí",ISNUMBER(E28)),E28,"")
A29: D3 | B29: 3.7 | C29: Gestión de cookies con plataforma de consentimiento, con registro de versiones y posibilidad de revocar. | D29: • 5.34 · Privacidad y protección de datos personales • 8.23 · Filtrado web | E29: =IFERROR(AVERAGE('Controles marcos'!$E$35,'Controles marcos'!$E$83),"") | J29: Extra (marco o buena práctica) | K29: No | L29: =IF(AND(K29="Sí",ISNUMBER(E29)),E29,"")
A30: D4 | B30: 4.1 | C30: Existe un procedimiento formal para atender solicitudes de derechos (acceso, rectificación, supresión, oposición y portabilidad) y un canal publicado para presentarlas. Verificar: procedimiento y canal visible para el titular. | D30: • Indicador automático: solicitudes ARCOP atendidas en plazo (hoja ARCOP) • 5.34 · Privacidad y protección de datos personales | E30: =IFERROR(AVERAGE(Resumen!$C$5,'Controles marcos'!$E$35),"") | J30: Obligatorio Ley 21.719 | K30: Sí | L30: =IF(AND(K30="Sí",ISNUMBER(E30)),E30,"")
A31: D4 | B31: 4.2 | C31: Los plazos de respuesta a las solicitudes están definidos y se monitorean. Verificar: plazo aplicado (según el texto oficial) y reporte de solicitudes fuera de plazo. | D31: • Indicador automático: solicitudes ARCOP atendidas en plazo (hoja ARCOP) | E31: =IFERROR(AVERAGE(Resumen!$C$5),"") | J31: Obligatorio Ley 21.719 | K31: Sí | L31: =IF(AND(K31="Sí",ISNUMBER(E31)),E31,"")
A32: D4 | B32: 4.3 | C32: Antes de entregar o modificar datos, se verifica la identidad del solicitante. Verificar: método de verificación usado. | D32: • 5.34 · Privacidad y protección de datos personales • 5.18 · Derechos de acceso | E32: =IFERROR(AVERAGE('Controles marcos'!$E$35,'Controles marcos'!$E$19),"") | J32: Obligatorio Ley 21.719 | K32: Sí | L32: =IF(AND(K32="Sí",ISNUMBER(E32)),E32,"")
A33: D4 | B33: 4.4 | C33: La organización puede ubicar, rectificar, suprimir, exportar y restringir los datos de una persona en todos sus sistemas. Verificar: prueba práctica con un caso real o de prueba. | D33: • 5.33 · Protección de registros • 8.10 · Eliminación de información | E33: =IFERROR(AVERAGE('Controles marcos'!$E$34,'Controles marcos'!$E$70),"") | J33: Obligatorio Ley 21.719 | K33: Sí | L33: =IF(AND(K33="Sí",ISNUMBER(E33)),E33,"")
A34: D4 | B34: 4.5 | C34: Cada solicitud, su respuesta y el motivo de cualquier rechazo quedan registrados. Verificar: hoja ARCOP completa. | D34: • 5.33 · Protección de registros | E34: =IFERROR(AVERAGE('Controles marcos'!$E$34),"") | J34: Obligatorio Ley 21.719 | K34: Sí | L34: =IF(AND(K34="Sí",ISNUMBER(E34)),E34,"")
A35: D4 | B35: 4.6 | C35: Si hay decisiones automatizadas que afectan al titular, se le informa y puede pedir revisión humana. Verificar: si existen decisiones automatizadas (por ejemplo, scoring de crédito o aprobación de clientes) y cómo se informan. | D35: • 5.34 · Privacidad y protección de datos personales | E35: =IFERROR(AVERAGE('Controles marcos'!$E$35),"") | J35: Obligatorio Ley 21.719 | K35: Sí | L35: =IF(AND(K35="Sí",ISNUMBER(E35)),E35,"")
A36: D4 | B36: 4.7 | C36: Procedimiento para solicitudes ARCOP que llegan por canales informales (WhatsApp, redes sociales, call center), con registro y plazo. | D36: • Indicador automático: solicitudes ARCOP atendidas en plazo (hoja ARCOP) • 5.34 · Privacidad y protección de datos personales | E36: =IFERROR(AVERAGE(Resumen!$C$5,'Controles marcos'!$E$35),"") | J36: Extra (marco o buena práctica) | K36: No | L36: =IF(AND(K36="Sí",ISNUMBER(E36)),E36,"")
A37: D4 | B37: 4.8 | C37: La organización puede localizar los datos de un titular en todos sus sistemas y proveedores dentro de un plazo razonable. Verificar: prueba con un caso real o de prueba que muestre los sistemas consultados y el tiempo empleado. | D37: • 5.33 · Protección de registros • 8.15 · Registro de actividades (logging) | E37: =IFERROR(AVERAGE('Controles marcos'!$E$34,'Controles marcos'!$E$75),"") | J37: Obligatorio Ley 21.719 | K37: Sí | L37: =IF(AND(K37="Sí",ISNUMBER(E37)),E37,"")
A38: D4 | B38: 4.9 | C38: Los datos entregados por portabilidad se exportan en un formato estructurado y de uso común. Verificar: archivo de ejemplo exportado y formato utilizado. | D38: • 5.34 · Privacidad y protección de datos personales | E38: =IFERROR(AVERAGE('Controles marcos'!$E$35),"") | J38: Obligatorio Ley 21.719 | K38: Sí | L38: =IF(AND(K38="Sí",ISNUMBER(E38)),E38,"")
A39: D4 | B39: 4.10 | C39: Una supresión llega también a los respaldos y a los proveedores, con un procedimiento para hacerlo en plazos definidos. Verificar: procedimiento escrito y último caso ejecutado. | D39: • 8.13 · Respaldo de información • 5.20 · Seguridad en contratos con proveedores | E39: =IFERROR(AVERAGE('Controles marcos'!$E$73,'Controles marcos'!$E$21),"") | J39: Obligatorio Ley 21.719 | K39: Sí | L39: =IF(AND(K39="Sí",ISNUMBER(E39)),E39,"")
A40: D5 | B40: 5.1 | C40: Los datos se usan solo para las finalidades declaradas al titular, sin usos incompatibles posteriores. Verificar: finalidades del aviso frente a usos reales en los sistemas. | D40: • 5.34 · Privacidad y protección de datos personales | E40: =IFERROR(AVERAGE('Controles marcos'!$E$35),"") | J40: Obligatorio Ley 21.719 | K40: Sí | L40: =IF(AND(K40="Sí",ISNUMBER(E40)),E40,"")
A41: D5 | B41: 5.2 | C41: Solo se recolectan y mantienen los datos estrictamente necesarios para la finalidad. Verificar: formularios con campos justificados y revisión de campos innecesarios. | D41: • 5.34 · Privacidad y protección de datos personales • 8.11 · Enmascaramiento de datos | E41: =IFERROR(AVERAGE('Controles marcos'!$E$35,'Controles marcos'!$E$71),"") | J41: Obligatorio Ley 21.719 | K41: Sí | L41: =IF(AND(K41="Sí",ISNUMBER(E41)),E41,"")
A42: D5 | B42: 5.3 | C42: Existen mecanismos para mantener los datos exactos y actualizados. Verificar: cómo se corrigen datos y con qué frecuencia se revisan. | D42: • 5.34 · Privacidad y protección de datos personales | E42: =IFERROR(AVERAGE('Controles marcos'!$E$35),"") | J42: Obligatorio Ley 21.719 | K42: Sí | L42: =IF(AND(K42="Sí",ISNUMBER(E42)),E42,"")
A43: D5 | B43: 5.4 | C43: Existe una política de retención con plazos concretos para cada categoría de dato. Verificar: tabla de retención con plazos y base legal. | D43: • 5.33 · Protección de registros | E43: =IFERROR(AVERAGE('Controles marcos'!$E$34),"") | J43: Obligatorio Ley 21.719 | K43: Sí | L43: =IF(AND(K43="Sí",ISNUMBER(E43)),E43,"")
A44: D5 | B44: 5.5 | C44: Al cumplirse el plazo, los datos se eliminan o anonimizan de forma segura, y queda evidencia. Verificar: registro de una eliminación reciente. | D44: • 8.10 · Eliminación de información | E44: =IFERROR(AVERAGE('Controles marcos'!$E$70),"") | J44: Obligatorio Ley 21.719 | K44: Sí | L44: =IF(AND(K44="Sí",ISNUMBER(E44)),E44,"")
A45: D5 | B45: 5.6 | C45: Los datos obtenidos de terceros o de fuentes públicas se validan en cuanto a su origen y licitud antes de usarlos. Verificar: origen documentado de cada base comprada o recibida. | D45: • 5.19 · Seguridad en relaciones con proveedores • 5.14 · Transferencia de información | E45: =IFERROR(AVERAGE('Controles marcos'!$E$20,'Controles marcos'!$E$15),"") | J45: Obligatorio Ley 21.719 | K45: Sí | L45: =IF(AND(K45="Sí",ISNUMBER(E45)),E45,"")
A46: D5 | B46: 5.7 | C46: Minimización en formularios web y POS: solo campos obligatorios justificados por la finalidad. | D46: • 5.34 · Privacidad y protección de datos personales • 8.11 · Enmascaramiento de datos | E46: =IFERROR(AVERAGE('Controles marcos'!$E$35,'Controles marcos'!$E$71),"") | J46: Extra (marco o buena práctica) | K46: No | L46: =IF(AND(K46="Sí",ISNUMBER(E46)),E46,"")
A47: D5 | B47: 5.8 | C47: Eliminación automática de datos según la tabla de retención. | D47: • 5.33 · Protección de registros • 8.10 · Eliminación de información | E47: =IFERROR(AVERAGE('Controles marcos'!$E$34,'Controles marcos'!$E$70),"") | J47: Extra (marco o buena práctica) | K47: No | L47: =IF(AND(K47="Sí",ISNUMBER(E47)),E47,"")
A48: D5 | B48: 5.9 | C48: Existe una tabla de retención por categoría de dato y las eliminaciones se ejecutan y quedan registradas. Verificar: último registro de eliminación, con fecha y responsable. | D48: • 5.33 · Protección de registros • 8.10 · Eliminación de información | E48: =IFERROR(AVERAGE('Controles marcos'!$E$34,'Controles marcos'!$E$70),"") | J48: Obligatorio Ley 21.719 | K48: Sí | L48: =IF(AND(K48="Sí",ISNUMBER(E48)),E48,"")
A49: D5 | B49: 5.10 | C49: Cada eliminación deja evidencia: qué se eliminó, cuándo, por quién y cómo se verificó. Verificar: muestra de tres registros de eliminación. | D49: • 8.10 · Eliminación de información | E49: =IFERROR(AVERAGE('Controles marcos'!$E$70),"") | J49: Obligatorio Ley 21.719 | K49: Sí | L49: =IF(AND(K49="Sí",ISNUMBER(E49)),E49,"")
A50: D6 | B50: 6.1 | C50: Los datos sensibles (salud, biométricos, origen, creencias, antecedentes penales) y los de menores están identificados en el inventario. Verificar: lista de datos sensibles por sistema. | D50: • 5.12 · Clasificación de la información • 5.9 · Inventario de información y activos | E50: =IFERROR(AVERAGE('Controles marcos'!$E$13,'Controles marcos'!$E$10),"") | J50: Obligatorio Ley 21.719 | K50: Sí | L50: =IF(AND(K50="Sí",ISNUMBER(E50)),E50,"")
A51: D6 | B51: 6.2 | C51: Para tratar datos sensibles se obtiene consentimiento explícito del titular. Verificar: formulario de consentimiento específico para datos sensibles. | D51: • 5.34 · Privacidad y protección de datos personales | E51: =IFERROR(AVERAGE('Controles marcos'!$E$35),"") | J51: Obligatorio Ley 21.719 | K51: Sí | L51: =IF(AND(K51="Sí",ISNUMBER(E51)),E51,"")
A52: D6 | B52: 6.3 | C52: Los datos sensibles tienen controles reforzados: acceso restringido, cifrado y registro de accesos. Verificar: matriz de acceso y logs de esos datos. | D52: • 8.11 · Enmascaramiento de datos • 8.24 · Uso de criptografía | E52: =IFERROR(AVERAGE('Controles marcos'!$E$71,'Controles marcos'!$E$84),"") | J52: Obligatorio Ley 21.719 | K52: Sí | L52: =IF(AND(K52="Sí",ISNUMBER(E52)),E52,"")
A53: D6 | B53: 6.4 | C53: Si se tratan datos de niños, niñas o adolescentes, se aplica el interés superior del menor y se obtiene el consentimiento de su representante cuando corresponde. Verificar: si hay tratamientos con menores y cómo se controlan. | D53: • 5.34 · Privacidad y protección de datos personales | E53: =IFERROR(AVERAGE('Controles marcos'!$E$35),"") | J53: Obligatorio Ley 21.719 | K53: Sí | L53: =IF(AND(K53="Sí",ISNUMBER(E53)),E53,"")
A54: D6 | B54: 6.5 | C54: El tratamiento biométrico y la vigilancia sistemática tienen restricciones y justificación escrita. Verificar: si existe biometría o vigilancia y su justificación. | D54: • 5.34 · Privacidad y protección de datos personales | E54: =IFERROR(AVERAGE('Controles marcos'!$E$35),"") | J54: Obligatorio Ley 21.719 | K54: Sí | L54: =IF(AND(K54="Sí",ISNUMBER(E54)),E54,"")
A55: D6 | B55: 6.6 | C55: Verificación de edad en ecommerce cuando se venden productos restringidos. | D55: • 5.34 · Privacidad y protección de datos personales | E55: =IFERROR(AVERAGE('Controles marcos'!$E$35),"") | J55: Extra (marco o buena práctica) | K55: No | L55: =IF(AND(K55="Sí",ISNUMBER(E55)),E55,"")
A56: D7 | B56: 7.1 | C56: Están definidos criterios de alto riesgo y se comunican a las áreas que proponen nuevos tratamientos. Verificar: criterios escritos y su difusión. | D56: • 5.34 · Privacidad y protección de datos personales | E56: =IFERROR(AVERAGE('Controles marcos'!$E$35),"") | J56: Obligatorio Ley 21.719 | K56: Sí | L56: =IF(AND(K56="Sí",ISNUMBER(E56)),E56,"")
A57: D7 | B57: 7.2 | C57: Se realiza una evaluación de impacto en protección de datos (EIPD/DPIA) antes de iniciar cada tratamiento de alto riesgo. Verificar: EIPD existentes y su fecha. | D57: • 5.34 · Privacidad y protección de datos personales • 5.8 · SI en gestión de proyectos | E57: =IFERROR(AVERAGE('Controles marcos'!$E$35,'Controles marcos'!$E$9),"") | J57: Obligatorio Ley 21.719 | K57: Sí | L57: =IF(AND(K57="Sí",ISNUMBER(E57)),E57,"")
A58: D7 | B58: 7.3 | C58: La privacidad se revisa como parte de la gestión de proyectos y de los cambios a sistemas. Verificar: checklist de privacidad en la metodología de proyectos. | D58: • 5.8 · SI en gestión de proyectos • 8.25 · Ciclo de vida de desarrollo seguro • 8.27 · Principios de arquitectura segura | E58: =IFERROR(AVERAGE('Controles marcos'!$E$9,'Controles marcos'!$E$85,'Controles marcos'!$E$87),"") | J58: Obligatorio Ley 21.719 | K58: Sí | L58: =IF(AND(K58="Sí",ISNUMBER(E58)),E58,"")
A59: D7 | B59: 7.4 | C59: Por defecto, los sistemas y productos tratan el mínimo de datos y dan el mínimo de accesos. Verificar: configuración por defecto en formularios y sistemas. | D59: • 8.9 · Gestión de la configuración | E59: =IFERROR(AVERAGE('Controles marcos'!$E$69),"") | J59: Obligatorio Ley 21.719 | K59: Sí | L59: =IF(AND(K59="Sí",ISNUMBER(E59)),E59,"")
A60: D7 | B60: 7.5 | C60: Si el riesgo residual de un tratamiento es alto, existe un procedimiento para consultar a la autoridad antes de iniciarlo. Verificar: procedimiento escrito. | D60: • 5.34 · Privacidad y protección de datos personales | E60: =IFERROR(AVERAGE('Controles marcos'!$E$35),"") | J60: Obligatorio Ley 21.719 | K60: Sí | L60: =IF(AND(K60="Sí",ISNUMBER(E60)),E60,"")
A61: D7 | B61: 7.6 | C61: Las decisiones que afectan a personas y se toman solo por sistemas automáticos están identificadas. Verificar: inventario de decisiones automatizadas (por ejemplo, scoring, aprobaciones o precios personalizados). | D61: • 5.34 · Privacidad y protección de datos personales | E61: =IFERROR(AVERAGE('Controles marcos'!$E$35),"") | J61: Obligatorio Ley 21.719 | K61: Sí | L61: =IF(AND(K61="Sí",ISNUMBER(E61)),E61,"")
A62: D7 | B62: 7.7 | C62: Ante una decisión automatizada, el titular puede pedir información sobre su lógica y solicitar revisión por una persona. Verificar: procedimiento escrito y un caso de prueba documentado. | D62: • 5.34 · Privacidad y protección de datos personales • 5.8 · SI en gestión de proyectos | E62: =IFERROR(AVERAGE('Controles marcos'!$E$35,'Controles marcos'!$E$9),"") | J62: Obligatorio Ley 21.719 | K62: Sí | L62: =IF(AND(K62="Sí",ISNUMBER(E62)),E62,"")
A63: D8 | B63: 8.1 | C63: Existe un sistema de gestión de seguridad de la información (ISO/IEC 27001) implementado o en implementación. Verificar: alcance del SGSI y su avance. | D63: • 5.1 · Políticas de seguridad de la información | E63: =IFERROR(AVERAGE('Controles marcos'!$E$2),"") | J63: Obligatorio Ley 21.719 | K63: Sí | L63: =IF(AND(K63="Sí",ISNUMBER(E63)),E63,"")
A64: D8 | B64: 8.2 | C64: El acceso a los sistemas sigue el principio de mínimo privilegio, con separación de funciones y revisión periódica. Verificar: matriz de accesos y última revisión. | D64: • 8.2 · Derechos de acceso privilegiado • 5.15 · Control de acceso | E64: =IFERROR(AVERAGE('Controles marcos'!$E$62,'Controles marcos'!$E$16),"") | J64: Obligatorio Ley 21.719 | K64: Sí | L64: =IF(AND(K64="Sí",ISNUMBER(E64)),E64,"")
A65: D8 | B65: 8.3 | C65: Todos los sistemas que contienen datos personales exigen autenticación multifactor (MFA). Verificar: lista de sistemas con MFA activo y los que no lo tienen. | D65: • 5.17 · Información de autenticación • 8.5 · Autenticación segura | E65: =IFERROR(AVERAGE('Controles marcos'!$E$18,'Controles marcos'!$E$65),"") | J65: Obligatorio Ley 21.719 | K65: Sí | L65: =IF(AND(K65="Sí",ISNUMBER(E65)),E65,"")
A66: D8 | B66: 8.4 | C66: Los datos se cifran en tránsito y en reposo, incluidos respaldos y equipos portátiles. Verificar: configuración de cifrado por sistema y en equipos. | D66: • 8.24 · Uso de criptografía | E66: =IFERROR(AVERAGE('Controles marcos'!$E$84),"") | J66: Obligatorio Ley 21.719 | K66: Sí | L66: =IF(AND(K66="Sí",ISNUMBER(E66)),E66,"")
A67: D8 | B67: 8.5 | C67: Las vulnerabilidades se corrigen con plazos según su criticidad. Verificar: último escaneo, hallazgos abiertos y plazos de parcheo. | D67: • 8.8 · Gestión de vulnerabilidades técnicas • CIS 7 · Gestión continua de vulnerabilidades | E67: =IFERROR(AVERAGE('Controles marcos'!$E$68,'Controles marcos'!$E$142),"") | J67: Obligatorio Ley 21.719 | K67: Sí | L67: =IF(AND(K67="Sí",ISNUMBER(E67)),E67,"")
A68: D8 | B68: 8.6 | C68: Los accesos a datos personales quedan registrados, los registros están protegidos y tienen plazo de retención. Verificar: logs de accesos y su retención. | D68: • 8.15 · Registro de actividades (logging) | E68: =IFERROR(AVERAGE('Controles marcos'!$E$75),"") | J68: Obligatorio Ley 21.719 | K68: Sí | L68: =IF(AND(K68="Sí",ISNUMBER(E68)),E68,"")
A69: D8 | B69: 8.7 | C69: Los respaldos están cifrados y se prueban restaurándolos. Verificar: última prueba de restauración documentada. | D69: • 8.13 · Respaldo de información | E69: =IFERROR(AVERAGE('Controles marcos'!$E$73),"") | J69: Obligatorio Ley 21.719 | K69: Sí | L69: =IF(AND(K69="Sí",ISNUMBER(E69)),E69,"")
A70: D8 | B70: 8.8 | C70: Se realizan pruebas de intrusión o evaluaciones técnicas al menos una vez al año, y los hallazgos críticos se cierran. Verificar: informe de pentest del último año. | D70: • 8.8 · Gestión de vulnerabilidades técnicas • 5.35 · Revisión independiente de SI | E70: =IFERROR(AVERAGE('Controles marcos'!$E$68,'Controles marcos'!$E$36),"") | J70: Obligatorio Ley 21.719 | K70: Sí | L70: =IF(AND(K70="Sí",ISNUMBER(E70)),E70,"")
A71: D8 | B71: 8.9 | C71: Los datos se seudonimizan o anonimizan cuando la finalidad lo permite. Verificar: casos donde se aplica y donde podría aplicarse. | D71: • 8.11 · Enmascaramiento de datos | E71: =IFERROR(AVERAGE('Controles marcos'!$E$71),"") | J71: Obligatorio Ley 21.719 | K71: Sí | L71: =IF(AND(K71="Sí",ISNUMBER(E71)),E71,"")
A72: D8 | B72: 8.10 | C72: Las cuentas privilegiadas (administradores) tienen control reforzado y sus sesiones quedan registradas. Verificar: lista de cuentas privilegiadas y herramienta de control. | D72: • 8.2 · Derechos de acceso privilegiado • 8.16 · Actividades de monitoreo | E72: =IFERROR(AVERAGE('Controles marcos'!$E$62,'Controles marcos'!$E$76),"") | J72: Obligatorio Ley 21.719 | K72: Sí | L72: =IF(AND(K72="Sí",ISNUMBER(E72)),E72,"")
A73: D8 | B73: 8.11 | C73: Los equipos de usuario tienen MDM, cifrado y EDR. Verificar: cobertura de cada herramienta sobre el parque de equipos. | D73: • 8.1 · Dispositivos de usuario final | E73: =IFERROR(AVERAGE('Controles marcos'!$E$61),"") | J73: Obligatorio Ley 21.719 | K73: Sí | L73: =IF(AND(K73="Sí",ISNUMBER(E73)),E73,"")
A74: D8 | B74: 8.12 | C74: Servidores y equipos tienen protección contra malware actualizada y monitoreada. Verificar: porcentaje de equipos con EDR y alertas recientes. | D74: • 8.7 · Protección contra malware • CIS 10 · Defensas contra malware | E74: =IFERROR(AVERAGE('Controles marcos'!$E$67,'Controles marcos'!$E$144),"") | J74: Obligatorio Ley 21.719 | K74: Sí | L74: =IF(AND(K74="Sí",ISNUMBER(E74)),E74,"")
A75: D8 | B75: 8.13 | C75: El acceso al código fuente y a la información está restringido por rol. Verificar: permisos del repositorio y de carpetas críticas. | D75: • 8.3 · Restricción de acceso a la información • 8.4 · Acceso al código fuente | E75: =IFERROR(AVERAGE('Controles marcos'!$E$63,'Controles marcos'!$E$64),"") | J75: Obligatorio Ley 21.719 | K75: Sí | L75: =IF(AND(K75="Sí",ISNUMBER(E75)),E75,"")
A76: D8 | B76: 8.14 | C76: Existen controles para evitar la fuga de datos (envíos masivos, copias a dispositivos externos). Verificar: reglas de DLP o equivalentes y su alerta. | D76: • 8.12 · Prevención de fuga de datos | E76: =IFERROR(AVERAGE('Controles marcos'!$E$72),"") | J76: Obligatorio Ley 21.719 | K76: Sí | L76: =IF(AND(K76="Sí",ISNUMBER(E76)),E76,"")
A77: D8 | B77: 8.15 | C77: Se controla la capacidad de los servicios y la sincronización horaria de los sistemas. Verificar: monitoreo de capacidad y configuración NTP. | D77: • 8.6 · Gestión de capacidad • 8.17 · Sincronización de relojes | E77: =IFERROR(AVERAGE('Controles marcos'!$E$66,'Controles marcos'!$E$77),"") | J77: Obligatorio Ley 21.719 | K77: Sí | L77: =IF(AND(K77="Sí",ISNUMBER(E77)),E77,"")
A78: D8 | B78: 8.16 | C78: Las redes están segmentadas y protegidas con firewalls y servicios de red seguros. Verificar: diagrama de red y reglas de firewall. | D78: • 8.20 · Seguridad en redes • 8.21 · Seguridad de los servicios de red • 8.22 · Segregación de redes • 8.23 · Filtrado web | E78: =IFERROR(AVERAGE('Controles marcos'!$E$80,'Controles marcos'!$E$81,'Controles marcos'!$E$82,'Controles marcos'!$E$83),"") | J78: Obligatorio Ley 21.719 | K78: Sí | L78: =IF(AND(K78="Sí",ISNUMBER(E78)),E78,"")
A79: D8 | B79: 8.17 | C79: Las herramientas de administración con privilegios están restringidas y solo se instala software autorizado. Verificar: lista de herramientas privilegiadas y de software permitido. | D79: • 8.18 · Uso de programas de utilidad con privilegios • 8.19 · Instalación de software en sistemas operativos • CIS 2 · Inventario de software | E79: =IFERROR(AVERAGE('Controles marcos'!$E$78,'Controles marcos'!$E$79,'Controles marcos'!$E$138),"") | J79: Obligatorio Ley 21.719 | K79: Sí | L79: =IF(AND(K79="Sí",ISNUMBER(E79)),E79,"")
A80: D8 | B80: 8.18 | C80: Las identidades y credenciales de usuarios, servicios y equipos se gestionan con procedimiento y registro. Verificar: proceso de alta y baja con tickets. | D80: • 5.16 · Gestión de identidades • NIST PR.AA-01 · Gestión de identidades y credenciales • NIST PR.AA-02 · Verificación de identidades • CIS 5 · Gestión de cuentas | E80: =IFERROR(AVERAGE('Controles marcos'!$E$17,'Controles marcos'!$E$113,'Controles marcos'!$E$114,'Controles marcos'!$E$140),"") | J80: Obligatorio Ley 21.719 | K80: Sí | L80: =IF(AND(K80="Sí",ISNUMBER(E80)),E80,"")
A81: D8 | B81: 8.19 | C81: Los accesos verifican la autenticación de cada usuario y protegen las aserciones de identidad. Verificar: configuración de autenticación y tokens. | D81: • NIST PR.AA-03 · Autenticación de usuarios, servicios y equipos • NIST PR.AA-04 · Protección de aserciones de identidad • 5.17 · Información de autenticación | E81: =IFERROR(AVERAGE('Controles marcos'!$E$115,'Controles marcos'!$E$116,'Controles marcos'!$E$18),"") | J81: Obligatorio Ley 21.719 | K81: Sí | L81: =IF(AND(K81="Sí",ISNUMBER(E81)),E81,"")
A82: D8 | B82: 8.20 | C82: Los permisos se asignan por mínimo privilegio y se revisan periódicamente. Verificar: última revisión de accesos (recertificación). | D82: • 5.18 · Derechos de acceso • NIST PR.AA-05 · Permisos con mínimo privilegio y separación de funciones • CIS 6 · Gestión del control de acceso | E82: =IFERROR(AVERAGE('Controles marcos'!$E$19,'Controles marcos'!$E$117,'Controles marcos'!$E$141),"") | J82: Obligatorio Ley 21.719 | K82: Sí | L82: =IF(AND(K82="Sí",ISNUMBER(E82)),E82,"")
A83: D8 | B83: 8.21 | C83: Los respaldos están protegidos, separados del sistema principal y resguardados. Verificar: ubicación de los respaldos y control de acceso. | D83: • NIST PR.DS-11 · Respaldos de datos | E83: =IFERROR(AVERAGE('Controles marcos'!$E$118),"") | J83: Obligatorio Ley 21.719 | K83: Sí | L83: =IF(AND(K83="Sí",ISNUMBER(E83)),E83,"")
A84: D8 | B84: 8.22 | C84: Las aplicaciones se desarrollan con requisitos de seguridad, codificación segura y pruebas antes de salir a producción. Verificar: procedimiento de desarrollo y evidencia de pruebas. | D84: • 8.26 · Requisitos de seguridad en aplicaciones • 8.28 · Codificación segura • 8.29 · Pruebas de seguridad en desarrollo y aceptación | E84: =IFERROR(AVERAGE('Controles marcos'!$E$86,'Controles marcos'!$E$88,'Controles marcos'!$E$89),"") | J84: Obligatorio Ley 21.719 | K84: Sí | L84: =IF(AND(K84="Sí",ISNUMBER(E84)),E84,"")
A85: D8 | B85: 8.23 | C85: Si se externaliza desarrollo, el proveedor cumple requisitos de seguridad, y los entornos de desarrollo, prueba y producción están separados. Verificar: contratos y diagrama de entornos. | D85: • 8.30 · Desarrollo externalizado • 8.31 · Separación de entornos • 8.33 · Información de prueba | E85: =IFERROR(AVERAGE('Controles marcos'!$E$90,'Controles marcos'!$E$91,'Controles marcos'!$E$93),"") | J85: Obligatorio Ley 21.719 | K85: Sí | L85: =IF(AND(K85="Sí",ISNUMBER(E85)),E85,"")
A86: D8 | B86: 8.24 | C86: Los cambios a sistemas en producción se aprueban, prueban y registran antes de implementarse. Verificar: registro de cambios de los últimos meses. | D86: • 8.32 · Gestión de cambios • COBIT BAI06 · proceso COBIT 5 | E86: =IFERROR(AVERAGE('Controles marcos'!$E$92,'Controles marcos'!$E$154),"") | J86: Obligatorio Ley 21.719 | K86: Sí | L86: =IF(AND(K86="Sí",ISNUMBER(E86)),E86,"")
A87: D8 | B87: 8.25 | C87: Existe un modelo RBAC documentado (roles, perfiles y matriz de accesos) revisado periódicamente. Verificar: matriz de roles y fecha de revisión. | D87: • 5.15 · Control de acceso • 5.18 · Derechos de acceso • NIST PR.AA-05 · Permisos con mínimo privilegio y separación de funciones • PCI Req 7 · Acceso restringido según necesidad de saber | E87: =IFERROR(AVERAGE('Controles marcos'!$E$16,'Controles marcos'!$E$19,'Controles marcos'!$E$117,'Controles marcos'!$E$160),"") | J87: Obligatorio Ley 21.719 | K87: Sí | L87: =IF(AND(K87="Sí",ISNUMBER(E87)),E87,"")
A88: D8 | B88: 8.26 | C88: El acceso al entorno de pagos exige autenticación fuerte según PCI DSS (requisitos 8). Verificar: MFA en acceso a entornos de pago. | D88: • 8.5 · Autenticación segura • PCI Req 8 · Identificación de usuarios y autenticación del acceso | E88: =IFERROR(AVERAGE('Controles marcos'!$E$65,'Controles marcos'!$E$161),"") | J88: Extra (marco o buena práctica) | K88: No | L88: =IF(AND(K88="Sí",ISNUMBER(E88)),E88,"")
A89: D8 | B89: 8.27 | C89: Los equipos del entorno de pagos tienen antivirus o EDR actualizado y monitoreado (PCI DSS requisito 5). Verificar: cobertura y última alerta. | D89: • 8.7 · Protección contra malware • PCI Req 5 · Protección de sistemas contra software malicioso | E89: =IFERROR(AVERAGE('Controles marcos'!$E$67,'Controles marcos'!$E$159),"") | J89: Extra (marco o buena práctica) | K89: No | L89: =IF(AND(K89="Sí",ISNUMBER(E89)),E89,"")
A90: D8 | B90: 8.28 | C90: Prevención de fuga de datos (DLP) en correo y nube. | D90: • 8.12 · Prevención de fuga de datos | E90: =IFERROR(AVERAGE('Controles marcos'!$E$72),"") | J90: Extra (marco o buena práctica) | K90: No | L90: =IF(AND(K90="Sí",ISNUMBER(E90)),E90,"")
A91: D8 | B91: 8.29 | C91: Política de dispositivos personales (BYOD) y de trabajo remoto con cifrado y borrado remoto. | D91: • 8.1 · Dispositivos de usuario final • 6.7 · Trabajo remoto | E91: =IFERROR(AVERAGE('Controles marcos'!$E$61,'Controles marcos'!$E$45),"") | J91: Extra (marco o buena práctica) | K91: No | L91: =IF(AND(K91="Sí",ISNUMBER(E91)),E91,"")
A92: D9 | B92: 9.1 | C92: Existe un procedimiento de respuesta a incidentes con roles y responsabilidades asignados. Verificar: procedimiento y nombres de responsables. | D92: • 5.24 · Planificación y preparación de gestión de incidentes • NIST RS.MA-01 · Plan de respuesta ejecutado con terceros • CIS 17 · Gestión de respuesta a incidentes | E92: =IFERROR(AVERAGE('Controles marcos'!$E$25,'Controles marcos'!$E$123,'Controles marcos'!$E$146),"") | J92: Obligatorio Ley 21.719 | K92: Sí | L92: =IF(AND(K92="Sí",ISNUMBER(E92)),E92,"")
A93: D9 | B93: 9.2 | C93: Existe un mecanismo para detectar y registrar vulneraciones que afecten datos personales. Verificar: fuentes de detección (alertas, reportes del personal) y registro. | D93: • 6.8 · Reporte de eventos de SI • 5.25 · Evaluación y decisión sobre eventos de SI • NIST RS.AN-07 · Recolección de datos del incidente | E93: =IFERROR(AVERAGE('Controles marcos'!$E$46,'Controles marcos'!$E$26,'Controles marcos'!$E$130),"") | J93: Obligatorio Ley 21.719 | K93: Sí | L93: =IF(AND(K93="Sí",ISNUMBER(E93)),E93,"")
A94: D9 | B94: 9.3 | C94: Las vulneraciones que afectan datos personales se notifican a la autoridad dentro del plazo legal. Verificar: plazo exacto según el texto oficial y el procedimiento que lo cumple. | D94: • 5.26 · Respuesta a incidentes de SI • L21.719 Art.14 sexies · Deber de reportar vulneraciones de seguridad | E94: =IFERROR(AVERAGE('Controles marcos'!$E$27,'Controles marcos'!$E$162),"") | J94: Obligatorio Ley 21.719 | K94: Sí | L94: =IF(AND(K94="Sí",ISNUMBER(E94)),E94,"")
A95: D9 | B95: 9.4 | C95: Cuando hay riesgo elevado para los titulares, se les notifica sin demora. Verificar: criterio de riesgo y canal de notificación. | D95: • 5.26 · Respuesta a incidentes de SI • NIST RS.CO-02 · Notificación a partes interesadas | E95: =IFERROR(AVERAGE('Controles marcos'!$E$27,'Controles marcos'!$E$132),"") | J95: Obligatorio Ley 21.719 | K95: Sí | L95: =IF(AND(K95="Sí",ISNUMBER(E95)),E95,"")
A96: D9 | B96: 9.5 | C96: Existen plantillas listas de notificación a la autoridad y a los titulares. Verificar: plantillas vigentes. | D96: • 5.26 · Respuesta a incidentes de SI • NIST RS.CO-03 · Información compartida con partes designadas | E96: =IFERROR(AVERAGE('Controles marcos'!$E$27,'Controles marcos'!$E$133),"") | J96: Obligatorio Ley 21.719 | K96: Sí | L96: =IF(AND(K96="Sí",ISNUMBER(E96)),E96,"")
A97: D9 | B97: 9.6 | C97: Se realiza al menos una vez al año un simulacro de brecha de datos personales. Verificar: fecha y resultados del último simulacro. | D97: • 5.24 · Planificación y preparación de gestión de incidentes | E97: =IFERROR(AVERAGE('Controles marcos'!$E$25),"") | J97: Obligatorio Ley 21.719 | K97: Sí | L97: =IF(AND(K97="Sí",ISNUMBER(E97)),E97,"")
A98: D9 | B98: 9.7 | C98: Cada vulneración queda registrada con causa raíz, impacto y acciones correctivas. Verificar: bitácora de incidentes. | D98: • 5.27 · Aprendizaje de los incidentes • NIST RS.AN-03 · Análisis de causa raíz | E98: =IFERROR(AVERAGE('Controles marcos'!$E$28,'Controles marcos'!$E$128),"") | J98: Obligatorio Ley 21.719 | K98: Sí | L98: =IF(AND(K98="Sí",ISNUMBER(E98)),E98,"")
A99: D9 | B99: 9.8 | C99: Existe un plan de continuidad y recuperación ante desastres con RTO y RPO definidos y probados. Verificar: plan, RTO y RPO por sistema y resultado de la última prueba. | D99: • 5.29 · Seguridad de la información durante disrupción • 5.30 · Preparación TIC para continuidad • 8.14 · Redundancia de instalaciones de procesamiento | E99: =IFERROR(AVERAGE('Controles marcos'!$E$30,'Controles marcos'!$E$31,'Controles marcos'!$E$74),"") | J99: Obligatorio Ley 21.719 | K99: Sí | L99: =IF(AND(K99="Sí",ISNUMBER(E99)),E99,"")
A100: D9 | B100: 9.9 | C100: Los incidentes se clasifican, priorizan y escalan con criterios escritos. Verificar: matriz de severidad y reglas de escalamiento. | D100: • NIST RS.MA-02 · Reportes de incidentes clasificados y validados • NIST RS.MA-03 · Incidentes categorizados y priorizados • NIST RS.MA-04 · Escalamiento de incidentes • NIST RS.MA-05 · Criterios para iniciar la recuperación | E100: =IFERROR(AVERAGE('Controles marcos'!$E$124,'Controles marcos'!$E$125,'Controles marcos'!$E$126,'Controles marcos'!$E$127),"") | J100: Obligatorio Ley 21.719 | K100: Sí | L100: =IF(AND(K100="Sí",ISNUMBER(E100)),E100,"")
...

Sheet Controles marcos
A1: Marco | B1: Control | C1: Nombre del control y qué debe levantar | D1: Tema / función | E1: Puntaje consolidado (automático desde Registro entrevistas) | F1: Referencia de evidencia (opcional) | G1: Usado en requisitos
A2: ISO 27001:2022 | B2: 5.1 | C2: Políticas de seguridad de la información. Qué debe levantar: Existe una política de seguridad aprobada por la dirección, con fecha de revisión y difundida al personal. | D2: 5. Controles Organizacionales | E2: =IF(COUNTIF('Registro entrevistas'!$F$30:$F$229,B2)=0,"",IF(COUNTIFS('Registro entrevistas'!$F$30:$F$229,B2,'Registro entrevistas'!$I$30:$I$229,"Sí")=0,IF(_xlfn.MINIFS('Registro entrevistas'!$J$30:$J$229,'Registro entrevistas'!$F$30:$F$229,B2)=0,"",MIN(3,_xlfn.MINIFS('Registro entrevistas'!$J$30:$J$229,'Registro entrevistas'!$F$30:$F$229,B2))),IF(_xlfn.MINIFS('Registro entrevistas'!$J$30:$J$229,'Registro entrevistas'!$F$30:$F$229,B2,'Registro entrevistas'!$I$30:$I$229,"Sí")=0,"",_xlfn.MINIFS('Registro entrevistas'!$J$30:$J$229,'Registro entrevistas'!$F$30:$F$229,B2,'Registro entrevistas'!$I$30:$I$229,"Sí")))) | G2: Sí
A3: ISO 27001:2022 | B3: 5.2 | C3: Roles y responsabilidades de SI. Qué debe levantar: Están definidos y documentados quién hace qué en seguridad (matriz de responsabilidades). | D3: 5. Controles Organizacionales | E3: =IF(COUNTIF('Registro entrevistas'!$F$30:$F$229,B3)=0,"",IF(COUNTIFS('Registro entrevistas'!$F$30:$F$229,B3,'Registro entrevistas'!$I$30:$I$229,"Sí")=0,IF(_xlfn.MINIFS('Registro entrevistas'!$J$30:$J$229,'Registro entrevistas'!$F$30:$F$229,B3)=0,"",MIN(3,_xlfn.MINIFS('Registro entrevistas'!$J$30:$J$229,'Registro entrevistas'!$F$30:$F$229,B3))),IF(_xlfn.MINIFS('Registro entrevistas'!$J$30:$J$229,'Registro entrevistas'!$F$30:$F$229,B3,'Registro entrevistas'!$I$30:$I$229,"Sí")=0,"",_xlfn.MINIFS('Registro entrevistas'!$J$30:$J$229,'Registro entrevistas'!$F$30:$F$229,B3,'Registro entrevistas'!$I$30:$I$229,"Sí")))) | G3: Sí
A4: ISO 27001:2022 | B4: 5.3 | C4: Segregación de funciones. Qué debe levantar: Las funciones incompatibles (por ejemplo, crear y aprobar pagos) están separadas o tienen control compensatorio. | D4: 5. Controles Organizacionales | E4: =IF(COUNTIF('Registro entrevistas'!$F$30:$F$229,B4)=0,"",IF(COUNTIFS('Registro entrevistas'!$F$30:$F$229,B4,'Registro entrevistas'!$I$30:$I$229,"Sí")=0,IF(_xlfn.MINIFS('Registro entrevistas'!$J$30:$J$229,'Registro entrevistas'!$F$30:$F$229,B4)=0,"",MIN(3,_xlfn.MINIFS('Registro entrevistas'!$J$30:$J$229,'Registro entrevistas'!$F$30:$F$229,B4))),IF(_xlfn.MINIFS('Registro entrevistas'!$J$30:$J$229,'Registro entrevistas'!$F$30:$F$229,B4,'Registro entrevistas'!$I$30:$I$229,"Sí")=0,"",_xlfn.MINIFS('Registro entrevistas'!$J$30:$J$229,'Registro entrevistas'!$F$30:$F$229,B4,'Registro entrevistas'!$I$30:$I$229,"Sí")))) | G4: Sí
A5: ISO 27001:2022 | B5: 5.4 | C5: Responsabilidades de la dirección. Qué debe levantar: La dirección revisa y respalda la seguridad: actas, compromisos y recursos asignados. | D5: 5. Controles Organizacionales | E5: =IF(COUNTIF('Registro entrevistas'!$F$30:$F$229,B5)=0,"",IF(COUNTIFS('Registro entrevistas'!$F$30:$F$229,B5,'Registro entrevistas'!$I$30:$I$229,"Sí")=0,IF(_xlfn.MINIFS('Registro entrevistas'!$J$30:$J$229,'Registro entrevistas'!$F$30:$F$229,B5)=0,"",MIN(3,_xlfn.MINIFS('Registro entrevistas'!$J$30:$J$229,'Registro entrevistas'!$F$30:$F$229,B5))),IF(_xlfn.MINIFS('Registro entrevistas'!$J$30:$J$229,'Registro entrevistas'!$F$30:$F$229,B5,'Registro entrevistas'!$I$30:$I$229,"Sí")=0,"",_xlfn.MINIFS('Registro entrevistas'!$J$30:$J$229,'Registro entrevistas'!$F$30:$F$229,B5,'Registro entrevistas'!$I$30:$I$229,"Sí")))) | G5: Sí
A6: ISO 27001:2022 | B6: 5.5 | C6: Contacto con autoridades. Qué debe levantar: Existen contactos definidos con autoridades (Agencia de Protección de Datos, CPLT, ANCI, policía) y canales conocidos. | D6: 5. Controles Organizacionales | E6: =IF(COUNTIF('Registro entrevistas'!$F$30:$F$229,B6)=0,"",IF(COUNTIFS('Registro entrevistas'!$F$30:$F$229,B6,'Registro entrevistas'!$I$30:$I$229,"Sí")=0,IF(_xlfn.MINIFS('Registro entrevistas'!$J$30:$J$229,'Registro entrevistas'!$F$30:$F$229,B6)=0,"",MIN(3,_xlfn.MINIFS('Registro entrevistas'!$J$30:$J$229,'Registro entrevistas'!$F$30:$F$229,B6))),IF(_xlfn.MINIFS('Registro entrevistas'!$J$30:$J$229,'Registro entrevistas'!$F$30:$F$229,B6,'Registro entrevistas'!$I$30:$I$229,"Sí")=0,"",_xlfn.MINIFS('Registro entrevistas'!$J$30:$J$229,'Registro entrevistas'!$F$30:$F$229,B6,'Registro entrevistas'!$I$30:$I$229,"Sí")))) | G6: Sí
A7: ISO 27001:2022 | B7: 5.6 | C7: Contacto con grupos de interés especial. Qué debe levantar: La organización participa en foros o CERT que entregan información de seguridad. | D7: 5. Controles Organizacionales | E7: =IF(COUNTIF('Registro entrevistas'!$F$30:$F$229,B7)=0,"",IF(COUNTIFS('Registro entrevistas'!$F$30:$F$229,B7,'Registro entrevistas'!$I$30:$I$229,"Sí")=0,IF(_xlfn.MINIFS('Registro entrevistas'!$J$30:$J$229,'Registro entrevistas'!$F$30:$F$229,B7)=0,"",MIN(3,_xlfn.MINIFS('Registro entrevistas'!$J$30:$J$229,'Registro entrevistas'!$F$30:$F$229,B7))),IF(_xlfn.MINIFS('Registro entrevistas'!$J$30:$J$229,'Registro entrevistas'!$F$30:$F$229,B7,'Registro entrevistas'!$I$30:$I$229,"Sí")=0,"",_xlfn.MINIFS('Registro entrevistas'!$J$30:$J$229,'Registro entrevistas'!$F$30:$F$229,B7,'Registro entrevistas'!$I$30:$I$229,"Sí")))) | G7: Sí
A8: ISO 27001:2022 | B8: 5.7 | C8: Inteligencia de amenazas. Qué debe levantar: Se recibe y analiza información sobre amenazas que pueden afectar a la organización. | D8: 5. Controles Organizacionales | E8: =IF(COUNTIF('Registro entrevistas'!$F$30:$F$229,B8)=0,"",IF(COUNTIFS('Registro entrevistas'!$F$30:$F$229,B8,'Registro entrevistas'!$I$30:$I$229,"Sí")=0,IF(_xlfn.MINIFS('Registro entrevistas'!$J$30:$J$229,'Registro entrevistas'!$F$30:$F$229,B8)=0,"",MIN(3,_xlfn.MINIFS('Registro entrevistas'!$J$30:$J$229,'Registro entrevistas'!$F$30:$F$229,B8))),IF(_xlfn.MINIFS('Registro entrevistas'!$J$30:$J$229,'Registro entrevistas'!$F$30:$F$229,B8,'Registro entrevistas'!$I$30:$I$229,"Sí")=0,"",_xlfn.MINIFS('Registro entrevistas'!$J$30:$J$229,'Registro entrevistas'!$F$30:$F$229,B8,'Registro entrevistas'!$I$30:$I$229,"Sí")))) | G8: Sí
A9: ISO 27001:2022 | B9: 5.8 | C9: SI en gestión de proyectos. Qué debe levantar: Los proyectos incluyen revisión de seguridad y privacidad desde su inicio. | D9: 5. Controles Organizacionales | E9: =IF(COUNTIF('Registro entrevistas'!$F$30:$F$229,B9)=0,"",IF(COUNTIFS('Registro entrevistas'!$F$30:$F$229,B9,'Registro entrevistas'!$I$30:$I$229,"Sí")=0,IF(_xlfn.MINIFS('Registro entrevistas'!$J$30:$J$229,'Registro entrevistas'!$F$30:$F$229,B9)=0,"",MIN(3,_xlfn.MINIFS('Registro entrevistas'!$J$30:$J$229,'Registro entrevistas'!$F$30:$F$229,B9))),IF(_xlfn.MINIFS('Registro entrevistas'!$J$30:$J$229,'Registro entrevistas'!$F$30:$F$229,B9,'Registro entrevistas'!$I$30:$I$229,"Sí")=0,"",_xlfn.MINIFS('Registro entrevistas'!$J$30:$J$229,'Registro entrevistas'!$F$30:$F$229,B9,'Registro entrevistas'!$I$30:$I$229,"Sí")))) | G9: Sí
A10: ISO 27001:2022 | B10: 5.9 | C10: Inventario de información y activos. Qué debe levantar: Existe un inventario de activos de información con dueño, clasificación y ubicación. | D10: 5. Controles Organizacionales | E10: =IF(COUNTIF('Registro entrevistas'!$F$30:$F$229,B10)=0,"",IF(COUNTIFS('Registro entrevistas'!$F$30:$F$229,B10,'Registro entrevistas'!$I$30:$I$229,"Sí")=0,IF(_xlfn.MINIFS('Registro entrevistas'!$J$30:$J$229,'Registro entrevistas'!$F$30:$F$229,B10)=0,"",MIN(3,_xlfn.MINIFS('Registro entrevistas'!$J$30:$J$229,'Registro entrevistas'!$F$30:$F$229,B10))),IF(_xlfn.MINIFS('Registro entrevistas'!$J$30:$J$229,'Registro entrevistas'!$F$30:$F$229,B10,'Registro entrevistas'!$I$30:$I$229,"Sí")=0,"",_xlfn.MINIFS('Registro entrevistas'!$J$30:$J$229,'Registro entrevistas'!$F$30:$F$229,B10,'Registro entrevistas'!$I$30:$I$229,"Sí")))) | G10: Sí
A11: ISO 27001:2022 | B11: 5.10 | C11: Uso aceptable de información. Qué debe levantar: Existe una política de uso aceptable de la información, firmada por los usuarios. | D11: 5. Controles Organizacionales | E11: =IF(COUNTIF('Registro entrevistas'!$F$30:$F$229,B11)=0,"",IF(COUNTIFS('Registro entrevistas'!$F$30:$F$229,B11,'Registro entrevistas'!$I$30:$I$229,"Sí")=0,IF(_xlfn.MINIFS('Registro entrevistas'!$J$30:$J$229,'Registro entrevistas'!$F$30:$F$229,B11)=0,"",MIN(3,_xlfn.MINIFS('Registro entrevistas'!$J$30:$J$229,'Registro entrevistas'!$F$30:$F$229,B11))),IF(_xlfn.MINIFS('Registro entrevistas'!$J$30:$J$229,'Registro entrevistas'!$F$30:$F$229,B11,'Registro entrevistas'!$I$30:$I$229,"Sí")=0,"",_xlfn.MINIFS('Registro entrevistas'!$J$30:$J$229,'Registro entrevistas'!$F$30:$F$229,B11,'Registro entrevistas'!$I$30:$I$229,"Sí")))) | G11: Sí
A12: ISO 27001:2022 | B12: 5.11 | C12: Devolución de activos. Qué debe levantar: Al salir o cambiar de cargo, el personal devuelve equipos e información, con registro. | D12: 5. Controles Organizacionales | E12: =IF(COUNTIF('Registro entrevistas'!$F$30:$F$229,B12)=0,"",IF(COUNTIFS('Registro entrevistas'!$F$30:$F$229,B12,'Registro entrevistas'!$I$30:$I$229,"Sí")=0,IF(_xlfn.MINIFS('Registro entrevistas'!$J$30:$J$229,'Registro entrevistas'!$F$30:$F$229,B12)=0,"",MIN(3,_xlfn.MINIFS('Registro entrevistas'!$J$30:$J$229,'Registro entrevistas'!$F$30:$F$229,B12))),IF(_xlfn.MINIFS('Registro entrevistas'!$J$30:$J$229,'Registro entrevistas'!$F$30:$F$229,B12,'Registro entrevistas'!$I$30:$I$229,"Sí")=0,"",_xlfn.MINIFS('Registro entrevistas'!$J$30:$J$229,'Registro entrevistas'!$F$30:$F$229,B12,'Registro entrevistas'!$I$30:$I$229,"Sí")))) | G12: Sí
A13: ISO 27001:2022 | B13: 5.12 | C13: Clasificación de la información. Qué debe levantar: La información se clasifica por nivel de sensibilidad y la clasificación se aplica en la práctica. | D13: 5. Controles Organizacionales | E13: =IF(COUNTIF('Registro entrevistas'!$F$30:$F$229,B13)=0,"",IF(COUNTIFS('Registro entrevistas'!$F$30:$F$229,B13,'Registro entrevistas'!$I$30:$I$229,"Sí")=0,IF(_xlfn.MINIFS('Registro entrevistas'!$J$30:$J$229,'Registro entrevistas'!$F$30:$F$229,B13)=0,"",MIN(3,_xlfn.MINIFS('Registro entrevistas'!$J$30:$J$229,'Registro entrevistas'!$F$30:$F$229,B13))),IF(_xlfn.MINIFS('Registro entrevistas'!$J$30:$J$229,'Registro entrevistas'!$F$30:$F$229,B13,'Registro entrevistas'!$I$30:$I$229,"Sí")=0,"",_xlfn.MINIFS('Registro entrevistas'!$J$30:$J$229,'Registro entrevistas'!$F$30:$F$229,B13,'Registro entrevistas'!$I$30:$I$229,"Sí")))) | G13: Sí
... A172: Normativa chilena | B172: L21.663 Ley de Ciberseguridad | C172: Ley 21.663 Marco de ciberseguridad. Qué debe levantar: Verificar si la organización está sujeta a la Ley 21.663 (servicios esenciales u operadores de importancia vital) y qué obligaciones de ciberseguridad y de reporte de incidentes le aplican. | D172: Normativa chilena | E172: =IF(COUNTIF('Registro entrevistas'!$F$30:$F$229,B172)=0,"",IF(COUNTIFS('Registro entrevistas'!$F$30:$F$229,B172,'Registro entrevistas'!$I$30:$I$229,"Sí")=0,IF(_xlfn.MINIFS('Registro entrevistas'!$J$30:$J$229,'Registro entrevistas'!$F$30:$F$229,B172)=0,"",MIN(3,_xlfn.MINIFS('Registro entrevistas'!$J$30:$J$229,'Registro entrevistas'!$F$30:$F$229,B172))),IF(_xlfn.MINIFS('Registro entrevistas'!$J$30:$J$229,'Registro entrevistas'!$F$30:$F$229,B172,'Registro entrevistas'!$I$30:$I$229,"Sí")=0,"",_xlfn.MINIFS('Registro entrevistas'!$J$30:$J$229,'Registro entrevistas'!$F$30:$F$229,B172,'Registro entrevistas'!$I$30:$I$229,"Sí")))) | G172: Sí

Sheet RAT
A1: ID | B1: Actividad / Proceso | C1: Finalidad del Tratamiento | D1: Base Legal (Art. 13) | E1: Categorías de Datos | F1: Datos Sensibles? (Art. 16) | G1: Categorías de Titulares | H1: Destinatarios / Receptores | I1: Transferencia Internacional | J1: País / Garantías | K1: Plazo Conservación | L1: Base Legal Conservación | M1: Medidas de Seguridad | N1: Sistema / Aplicación | O1: Responsable Interno | P1: Última Revisión | Q1: Fuente de los datos | R1: Cómo se recolectan | S1: Ubicación del almacenamiento | T1: Forma de eliminación | U1: Encargados (proveedores que tratan datos) | V1: Decisiones automatizadas | W1: Nivel de riesgo | X1: Requiere evaluación de impacto (EIPD) | Y1: Derechos ARCOP que aplican | Z1: Estado de la actividad | AA1: Completitud (1 = todos los campos)
A2: Info: | C2: Una fila por actividad. Todos los campos son obligatorios según Art. 14 bis Ley 21.719. | AA2: =IF(LEFT(A2,4)="RAT-",COUNTA(B2:Z2)/25,"")
A3: RAT-001 | B3: Gestión de clientes y contratos | C3: Ejecutar relación contractual: facturación, comunicaciones y soporte | D3: Lit. b — Ejecución de contrato | E3: Nombre, RUT, dirección, correo, teléfono, datos de facturación | F3: No | G3: Clientes personas naturales y contactos de personas jurídicas | H3: SII (obligación tributaria), proveedores de facturación electrónica | I3: Sí — SII | J3: Chile | K3: 6 años desde último documento tributario (Código Tributario) | L3: Lit. c — Obligación legal | M3: Cifrado en tránsito y reposo, control de acceso RBAC, backup diario | N3: CRM / ERP corporativo | O3: Gerencia Comercial | P3: 01/06/2026 | AA3: =IF(LEFT(A3,4)="RAT-",COUNTA(B3:Z3)/25,"")
A4: RAT-002 | B4: Gestión de recursos humanos | C4: Administrar ciclo de vida laboral: contratación, nómina, liquidaciones | D4: Lit. b — Ejecución de contrato; Lit. c — Obligación legal | E4: Nombre, RUT, dirección, licencias médicas, datos bancarios, cargas | F4: Sí — Datos de salud | G4: Empleados y ex-empleados | H4: AFP, ISAPRE/FONASA, Inspección del Trabajo, Mutualidades | I4: Sí — Previred, AFP, ISAPRE | J4: Chile | K4: 5 años desde desvinculación (Código del Trabajo Art. 510) | L4: Lit. c — Obligación legal | M4: Cifrado, acceso restringido RRHH, logs de auditoría | N4: Sistema RRHH / Payroll | O4: Gerencia RRHH | P4: 01/06/2026 | AA4: =IF(LEFT(A4,4)="RAT-",COUNTA(B4:Z4)/25,"")
A5: RAT-003 | B5: Marketing y comunicaciones comerciales | C5: Envío de newsletter, promociones y actualizaciones de productos | D5: Lit. a — Consentimiento expreso | E5: Nombre, correo electrónico, preferencias, historial de interacciones | F5: No | G5: Leads, prospectos y clientes con consentimiento | H5: Plataforma de email marketing (Mailchimp — EE.UU.) | I5: Sí — Mailchimp / EE.UU. | J5: EE.UU. — DPA firmado + SCCs | K5: Hasta revocación del consentimiento + 30 días | L5: Lit. a — Consentimiento (revocable en cualquier momento) | M5: Registro de consentimientos con timestamp, opt-out inmediato | N5: Plataforma email marketing | O5: Gerencia Marketing | P5: 01/06/2026 | AA5: =IF(LEFT(A5,4)="RAT-",COUNTA(B5:Z5)/25,"")
A6: RAT-004 | B6: Gestión de proveedores | C6: Administrar relación con proveedores, pagos y cumplimiento contractual | D6: Lit. b — Ejecución de contrato | E6: Nombre del contacto, RUT empresa, correo, teléfono, datos bancarios | F6: No | G6: Contactos y representantes de proveedores | H6: SII, banco para transferencias | I6: Sí — Bancos | J6: Chile | K6: 6 años desde último documento tributario | L6: Lit. c — Obligación legal | M6: Control de acceso, cifrado datos bancarios, logs de transacciones | N6: ERP / Sistema de proveedores | O6: Gerencia de Administración | P6: 01/06/2026 | AA6: =IF(LEFT(A6,4)="RAT-",COUNTA(B6:Z6)/25,"")
A7: RAT-005 | B7: Seguridad de la información y control de acceso | C7: Gestionar accesos, registrar actividad y detectar incidentes | D7: Lit. e — Interés legítimo del responsable | E7: Nombre de usuario, IP, logs de acceso, acciones en sistemas | F7: No | G7: Empleados y contratistas con acceso a sistemas | H7: Proveedores de SIEM/SOC (si aplica) | I7: Depende del proveedor | J7: Según contrato con proveedor | K7: 12 meses (ISO 27001 A.8.15); 3 años para incidentes | L7: Lit. e — Interés legítimo (seguridad corporativa) | M7: SIEM, logs cifrados, acceso restringido equipo de seguridad | N7: SIEM / Sistemas de logging | O7: CISO / TI | P7: 01/06/2026 | AA7: =IF(LEFT(A7,4)="RAT-",COUNTA(B7:Z7)/25,"")
A8: RAT-006 | B8: Atención al cliente y ejercicio de derechos ARCOP | C8: Gestionar solicitudes, reclamos y derechos ARCOP de titulares | D8: Lit. b — Ejecución de contrato; Lit. c — Obligación legal | E8: Nombre, correo, teléfono, descripción del requerimiento | F8: No | G8: Clientes y titulares que ejercen derechos | H8: Plataforma de tickets (helpdesk) | I8: No (proveedor en Chile) | J8: Chile | K8: 2 años desde cierre; indefinido para solicitudes ARCOP | L8: Lit. b y Lit. c — Obligación de respuesta Ley 21.719 | M8: Control de acceso, registro de solicitudes ARCOP, trazabilidad | N8: Sistema de tickets / CRM | O8: Servicio al Cliente | P8: 01/06/2026 | AA8: =IF(LEFT(A8,4)="RAT-",COUNTA(B8:Z8)/25,"")
AA9: =IF(LEFT(A9,4)="RAT-",COUNTA(B9:Z9)/25,"")
AA10: =IF(LEFT(A10,4)="RAT-",COUNTA(B10:Z10)/25,"")
AA11: =IF(LEFT(A11,4)="RAT-",COUNTA(B11:Z11)/25,"")
AA12: =IF(LEFT(A12,4)="RAT-",COUNTA(B12:Z12)/25,"")
AA13: =IF(LEFT(A13,4)="RAT-",COUNTA(B13:Z13)/25,"")
AA14: =IF(LEFT(A14,4)="RAT-",COUNTA(B14:Z14)/25,"")
AA15: =IF(LEFT(A15,4)="RAT-",COUNTA(B15:Z15)/25,"")
AA16: =IF(LEFT(A16,4)="RAT-",COUNTA(B16:Z16)/25,"")
AA17: =IF(LEFT(A17,4)="RAT-",COUNTA(B17:Z17)/25,"")
AA18: =IF(LEFT(A18,4)="RAT-",COUNTA(B18:Z18)/25,"")
AA19: =IF(LEFT(A19,4)="RAT-",COUNTA(B19:Z19)/25,"")
AA20: =IF(LEFT(A20,4)="RAT-",COUNTA(B20:Z20)/25,"")
... AA60: =IF(LEFT(A60,4)="RAT-",COUNTA(B60:Z60)/25,"")

Sheet ARCOP
A1: ID | B1: Titular (iniciales) | C1: Tipo de Derecho | D1: Fecha Recepción | E1: Fecha Límite (30 días corridos) | F1: Fecha Respuesta | G1: Estado | H1: Observaciones | I1: Estado de plazo
A2: Plazo legal: 30 días corridos desde la recepción (Art. 22, Ley 21.719). Extensible por 15 días adicionales con notificación escrita al titular. | I2: =IF(LEFT(A2,4)="ARC-",IF(ISNUMBER(F2),IF(F2<=E2,"A tiempo","Fuera de plazo"),IF(TODAY()>E2,"Vencida","En plazo")),"")
A3: ARC-001 | B3: J.G.M. | C3: Acceso | D3: 46157 | E3: 46187 | F3: 46162 | G3: Respondido | H3: Titular solicitó copia de todos sus datos. Entregado en formato estructurado. | I3: =IF(LEFT(A3,4)="ARC-",IF(ISNUMBER(F3),IF(F3<=E3,"A tiempo","Fuera de plazo"),IF(TODAY()>E3,"Vencida","En plazo")),"")
A4: ARC-002 | B4: M.F.R. | C4: Rectificación | D4: 46162 | E4: 46192 | F4: 46170 | G4: Respondido | H4: Corrección de correo electrónico y teléfono de contacto. | I4: =IF(LEFT(A4,4)="ARC-",IF(ISNUMBER(F4),IF(F4<=E4,"A tiempo","Fuera de plazo"),IF(TODAY()>E4,"Vencida","En plazo")),"")
A5: ARC-003 | B5: C.A.L. | C5: Cancelación / Supresión | D5: 46174 | E5: 46204 | G5: En proceso | H5: Verificando obligaciones legales que pudieran impedir la eliminación total. | I5: =IF(LEFT(A5,4)="ARC-",IF(ISNUMBER(F5),IF(F5<=E5,"A tiempo","Fuera de plazo"),IF(TODAY()>E5,"Vencida","En plazo")),"")
A6: ARC-004 | B6: R.M.V. | C6: Portabilidad | D6: 46176 | E6: 46206 | G6: Pendiente | H6: Preparando datos en formato estructurado y legible por máquina. | I6: =IF(LEFT(A6,4)="ARC-",IF(ISNUMBER(F6),IF(F6<=E6,"A tiempo","Fuera de plazo"),IF(TODAY()>E6,"Vencida","En plazo")),"")
I7: =IF(LEFT(A7,4)="ARC-",IF(ISNUMBER(F7),IF(F7<=E7,"A tiempo","Fuera de plazo"),IF(TODAY()>E7,"Vencida","En plazo")),"")
I8: =IF(LEFT(A8,4)="ARC-",IF(ISNUMBER(F8),IF(F8<=E8,"A tiempo","Fuera de plazo"),IF(TODAY()>E8,"Vencida","En plazo")),"")
I9: =IF(LEFT(A9,4)="ARC-",IF(ISNUMBER(F9),IF(F9<=E9,"A tiempo","Fuera de plazo"),IF(TODAY()>E9,"Vencida","En plazo")),"")
I10: =IF(LEFT(A10,4)="ARC-",IF(ISNUMBER(F10),IF(F10<=E10,"A tiempo","Fuera de plazo"),IF(TODAY()>E10,"Vencida","En plazo")),"")
I11: =IF(LEFT(A11,4)="ARC-",IF(ISNUMBER(F11),IF(F11<=E11,"A tiempo","Fuera de plazo"),IF(TODAY()>E11,"Vencida","En plazo")),"")
I12: =IF(LEFT(A12,4)="ARC-",IF(ISNUMBER(F12),IF(F12<=E12,"A tiempo","Fuera de plazo"),IF(TODAY()>E12,"Vencida","En plazo")),"")
I13: =IF(LEFT(A13,4)="ARC-",IF(ISNUMBER(F13),IF(F13<=E13,"A tiempo","Fuera de plazo"),IF(TODAY()>E13,"Vencida","En plazo")),"")
I14: =IF(LEFT(A14,4)="ARC-",IF(ISNUMBER(F14),IF(F14<=E14,"A tiempo","Fuera de plazo"),IF(TODAY()>E14,"Vencida","En plazo")),"")
I15: =IF(LEFT(A15,4)="ARC-",IF(ISNUMBER(F15),IF(F15<=E15,"A tiempo","Fuera de plazo"),IF(TODAY()>E15,"Vencida","En plazo")),"")
I16: =IF(LEFT(A16,4)="ARC-",IF(ISNUMBER(F16),IF(F16<=E16,"A tiempo","Fuera de plazo"),IF(TODAY()>E16,"Vencida","En plazo")),"")
I17: =IF(LEFT(A17,4)="ARC-",IF(ISNUMBER(F17),IF(F17<=E17,"A tiempo","Fuera de plazo"),IF(TODAY()>E17,"Vencida","En plazo")),"")
I18: =IF(LEFT(A18,4)="ARC-",IF(ISNUMBER(F18),IF(F18<=E18,"A tiempo","Fuera de plazo"),IF(TODAY()>E18,"Vencida","En plazo")),"")
... I60: =IF(LEFT(A60,4)="ARC-",IF(ISNUMBER(F60),IF(F60<=E60,"A tiempo","Fuera de plazo"),IF(TODAY()>E60,"Vencida","En plazo")),"")

Sheet Transferencias
A1: ID RAT | B1: Destinatario | C1: País | D1: Categoría Datos | E1: Finalidad | F1: Base Legal Transferencia | G1: Garantías Adoptadas | H1: Estado Adecuación | I1: Observaciones | J1: Garantía definida
A2: RAT-003 | B2: Mailchimp (Intuit Inc.) | C2: EE.UU. | D2: Nombre, email, preferencias | E2: Email marketing | F2: Consentimiento + DPA firmado | G2: SCCs (Cláusulas Contractuales Tipo) + DPA | H2: Sin decisión de adecuación CPLT — usar SCCs | I2: Revisar anualmente | J2: =IF(LEFT(A2,4)="RAT-",IF(LEN(G2)>0,"Sí","No"),"")
A3: RAT-002 | B3: Previred S.A. | C3: Chile | D3: RUT, salario, cargas familiares | E3: Cotizaciones previsionales | F3: Obligación legal (DL 3.500) | G3: Obligación legal chilena — no requiere garantía adicional | H3: N/A — Entidad sujeta a regulación CMF Chile | I3: Proveedor regulado | J3: =IF(LEFT(A3,4)="RAT-",IF(LEN(G3)>0,"Sí","No"),"")
A4: RAT-005 | B4: Proveedor SIEM cloud | C4: EE.UU. / UE | D4: Logs de usuario, IP, eventos de seguridad | E4: Seguridad y detección de amenazas | F4: Interés legítimo + DPA | G4: DPA + Certificación SOC 2 Type II | H4: Evaluar según proveedor contratado | I4: Verificar ubicación de datacenters y sub-encargados | J4: =IF(LEFT(A4,4)="RAT-",IF(LEN(G4)>0,"Sí","No"),"")
A5: Art. 25 Ley 21.719: Transferencias internacionales permitidas solo a países con nivel adecuado o mediante garantías contractuales equivalentes. El CPLT publicará la lista de países adecuados. | J5: =IF(LEFT(A5,4)="RAT-",IF(LEN(G5)>0,"Sí","No"),"")
J6: =IF(LEFT(A6,4)="RAT-",IF(LEN(G6)>0,"Sí","No"),"")
J7: =IF(LEFT(A7,4)="RAT-",IF(LEN(G7)>0,"Sí","No"),"")
J8: =IF(LEFT(A8,4)="RAT-",IF(LEN(G8)>0,"Sí","No"),"")
J9: =IF(LEFT(A9,4)="RAT-",IF(LEN(G9)>0,"Sí","No"),"")
J10: =IF(LEFT(A10,4)="RAT-",IF(LEN(G10)>0,"Sí","No"),"")
J11: =IF(LEFT(A11,4)="RAT-",IF(LEN(G11)>0,"Sí","No"),"")
J12: =IF(LEFT(A12,4)="RAT-",IF(LEN(G12)>0,"Sí","No"),"")
J13: =IF(LEFT(A13,4)="RAT-",IF(LEN(G13)>0,"Sí","No"),"")
J14: =IF(LEFT(A14,4)="RAT-",IF(LEN(G14)>0,"Sí","No"),"")
J15: =IF(LEFT(A15,4)="RAT-",IF(LEN(G15)>0,"Sí","No"),"")
J16: =IF(LEFT(A16,4)="RAT-",IF(LEN(G16)>0,"Sí","No"),"")
J17: =IF(LEFT(A17,4)="RAT-",IF(LEN(G17)>0,"Sí","No"),"")
... J60: =IF(LEFT(A60,4)="RAT-",IF(LEN(G60)>0,"Sí","No"),"")

Sheet Escala
A1: Puntaje | B1: Nivel | C1: Criterio
A2: 1 | B2: No existe | C2: No hay control ni práctica documentada.
A3: 2 | B3: Inicial | C3: Práctica informal o parcial, sin documentación ni responsable definido.
A4: 3 | B4: Definido | C4: Control documentado con responsable, aplicado de forma inconsistente o sin evidencia completa.
A5: 4 | B5: Implementado | C5: Control aplicado en la operación, con evidencia disponible.
A6: 5 | B6: Optimizado | C6: Control implementado, evidenciado, medido y revisado periódicamente.
A8: Madurez | B8: Rango | C8: Interpretación
A9: Crítico | B9: 1.0 – 1.9 | C9: Exposición alta a sanciones. Plan inmediato.
A10: Inicial | B10: 2.0 – 2.9 | C10: Brechas significativas. Priorizar D1, D2, D3 y D9.
A11: En desarrollo | B11: 3.0 – 3.9 | C11: Base instalada con brechas de evidencia y consistencia.
A12: Avanzado | B12: 4.0 – 4.5 | C12: Cumplimiento sólido. Foco en medición y auditoría.
A13: Optimizado | B13: 4.6 – 5.0 | C13: Madurez con mejora continua demostrable.

Sheet Notas
A1: NOTAS DE USO Y VERIFICACIÓN
A2: 1. Regla de puntaje: cada requisito legal toma el promedio de sus controles mapeados (y de sus indicadores RAT, ARCOP o transferencias cuando corresponden). No hay puntaje manual.
A3: 2. Controles sin requisito asociado: 0 controles del catálogo no están mapeados a ningún requisito y no afectan el total. Están marcados 'No' en la columna 'Usado en requisitos' de la hoja Controles marcos. Revisar si corresponde mapearlos.
A4: 3. ARCOP: el estado de plazo se calcula con la fecha de hoy. Hoy hay solicitudes vencidas (ARC-003 y ARC-004, con plazos de julio de 2026). Ver el indicador de la hoja Resumen.
A5: 4. Plazo de notificación de vulneraciones: las fuentes consultadas no coinciden (algunas indican 72 horas y otras, notificar sin dilación indebida). Confirmar en la BCN antes de fijar plazos internos.
A6: 5. Vigencia: la ley entra en vigencia el 1 de diciembre de 2026. Hay un proyecto para postergarla a diciembre de 2027; verificar su estado.
A7: 6. Las referencias a artículos y los controles de los marcos vienen de los documentos del proyecto y no se verificaron una por una contra el texto oficial.
A8: 7. PCI DSS y COBIT aplican solo si la organización procesa tarjetas o gestiona esos procesos. Usar N/A con justificación cuando no correspondan.
A9: 8. Benchmark BM-CONT (contenedores) no está mapeado a ningún requisito; se agregó solo al catálogo.
A10: 9. PCI DSS: el alcance del txt incluye solo los requisitos 2, 5, 7 y 8. Los requisitos 3, 4, 6, 10, 11 y 12 no están en el catálogo. Agregarlos cambia el alcance cotizado y debe confirmarse antes.
A11: 10. Esta herramienta es de autoevaluación y no constituye asesoría legal.
A12: 11. Meta objetivo: la escala 1 a 5 sigue la lógica de los modelos de capacidad y madurez (COBIT 5). El nivel 4 (Implementado) indica control operando con evidencia; el nivel 5 (Optimizado) se reserva para procesos críticos. La meta base es 4,0 y se ajusta según criterios de riesgo (impacto y exposición, enfoque ISO/IEC 27005): datos sensibles o de menores a gran escala, decisiones automatizadas, transferencias o muchos proveedores externos, y videovigilancia o biometría. Cada criterio que aplica suma 0,25, con tope de 4,5. Es un criterio de gestión propuesto, no un requisito numérico de la ley. Cualquier ajuste debe justificarse por escrito.

Sheet Listas
A1: Base legal (Art. 13) | B1: Tipo de derecho ARCOP | C1: Estado ARCOP | D1: Sí / No | E1: Puntaje
A2: Lit. a — Consentimiento expreso | B2: Acceso | C2: Pendiente | D2: Sí | E2: 1
A3: Lit. b — Ejecución de contrato | B3: Rectificación | C3: En proceso | D3: No | E3: 2
A4: Lit. c — Obligación legal | B4: Cancelación / Supresión | C4: Respondido | E4: 3
A5: Lit. d — Interés vital | B5: Oposición | C5: Rechazado | E5: 4
A6: Lit. e — Interés legítimo | B6: Portabilidad | E6: 5
A7: Lit. f — Interés público o autoridad pública | B7: Decisiones automatizadas | E7: N/A
